Workbook

Sheet Cover Page
B2: ESKAY CREEK
B3: Net Asset Value Model
B4: Skeena Gold & Silver | TSX: SKE | NYSE: SKE
B6: Last Updated | C6: March 13, 2026 | D6: ← Update this date when refreshing inputs
B7: Prepared By | C7: Kyle Tsuji
B8: Model Version | C8: 1
B9: Comps Last Updated | C9: =Comps!C5 -> 46094 | D9: ← Linked from Comps sheet
B10: INPUTS TO UPDATE PERIODICALLY | F10: NAV SUMMARY
B11: Input | C11: Current Value | D11: Source / Where to Find | F11: Active Scenario | G11: ='NAV Model'!C14 -> Base
B12: MARKET DATA | F12: NAV (US$ mm) | G12: ='NAV Model'!C6 -> 6383.9423
B13: Current Share Price (C$) | C13: ='NAV Model'!C8*'NAV Model'!$C$24 -> 43.1002 | D13: Yahoo Finance / Bloomberg | F13: NAV per Share (C$) | G13: ='NAV Model'!C7*'NAV Model'!$C$24 -> 72.102234
B14: Shares Outstanding (mm) | C14: ='NAV Model'!C32 -> 121.3 | D14: Latest quarterly filing (MD&A) | F14: Share Price (C$) | G14: =C13 -> 43.1002
B15: USD/CAD Exchange Rate | C15: ='NAV Model'!C24 -> 1.37 | D15: Bank of Canada / xe.com | F15: P/NAV Multiple | G15: ='NAV Model'!C9 -> 0.59776511
F16: Mine Life (Years) | G16: ='NAV Model'!C10 -> 12
B17: BALANCE SHEET DATA | F17: LOM Gold Production (koz) | G17: ='NAV Model'!C11 -> 2723.6147
B18: Cash & Equivalents (C$ 000s) | C18: ='Balance Sheet'!B7 -> 96941 | D18: Quarterly financial statements | F18: LT Gold Price (US$/oz) | G18: ='NAV Model'!C18 -> 3150
B19: Lease Liabilities — Current (C$ 000s) | C19: ='Balance Sheet'!B20 -> 6303 | D19: Quarterly financial statements | F19: Discount Rate | G19: ='NAV Model'!C25 -> 0.05
B20: Lease Liabilities — Non-current (C$ 000s) | C20: ='Balance Sheet'!B24 -> 7230 | D20: Quarterly financial statements
B21: Gold Stream Derivative (C$ 000s) | C21: ='Balance Sheet'!B25 -> 63886 | D21: Quarterly financial statements | F21: Valuation Summary
B22: → Net Debt (negative = net cash) (US$ mm) | C22: =(SUM(C19:C21)-C18)/1000/'NAV Model'!C24 -> -14.249635 | D22: Auto-calculated from above | F22: Valuation Method | G22: Implied Value (C$) | H22: Weight
F23: Comps: P/NAV | G23: =Comps!O27 -> 59.844854 | H23: 0.4
B24: COMMODITY PRICE SCENARIOS | F24: Comps: EV/Reserves | G24: =Comps!P27 -> 50.50882 | H24: 0.2
B25: Active Scenario | C25: ='NAV Model'!C14 -> Base | D25: Change via dropdown on NAV Model!B15 | F25: Comps: EV/Resources | G25: =Comps!Q27 -> 38.222004 | H25: 0.1
B26: Gold & Silver Price Assumptions | C26: See table → | D26: Edit on Economic Assumptions (E4:I17) | F26: Precedents: P/NAV | G26: =PTA!J24 -> 79.312457 | H26: 0.1
F27: Analyst Targets | G27: ='Broker Summary'!D12 -> 52.2 | H27: 0.2
B28: MODEL ASSUMPTIONS (change less frequently) | F28: Blended Valuation (C$) | G28: =SUMPRODUCT(G23:G27,H23:H27) -> 56.233152
B29: Discount Rate (WACC) | C29: ='NAV Model'!C25 -> 0.05 | D29: Technical report | F29: Current Share Price (C$) | G29: =C13 -> 43.1002
B30: Royalty Rate (NSR) | C30: ='NAV Model'!C26 -> 0.02 | D30: Technical report / royalty agreements | F30: Implied Upside | G30: =G28/G29-1 -> 0.30470744
B31: Corporate Tax Rate | C31: ='NAV Model'!C27 -> 0.27 | D31: Technical report / BC mining tax + federal rate
B32: Depreciation Method | C32: ='NAV Model'!C37 -> Units-of-Production | D32: Units-of-Production recommended
B33: Depreciable Asset Base (US$ mm) | C33: ='NAV Model'!C34 -> 520.43796 | D33: Pre-prod capex from technical report
B34: Closure Cost (US$ mm) | C34: ='NAV Model'!C39 -> 127.59124 | D34: Technical report / updated estimates | F34: Valuation Summary
F35: Valuation Method | G35: Low (C$) | H35: Difference | I35: High (C$)
B36: PERIODIC UPDATE CHECKLIST | F36: Comps: P/NAV | G36: =Comps!O29 -> 23.793737 | H36: =I36-G36 -> 56.960765 | I36: =Comps!O28 -> 80.754502
B37: Frequency | C37: Action | D37: Location | F37: Comps: EV/Reserves | G37: =Comps!P29 -> 18.510832 | H37: =I37-G37 -> 56.79761 | I37: =Comps!P28 -> 75.308441
B38: Daily / Weekly | C38: Update share price | D38: NAV Model → B8 | F38: Comps: EV/Resources | G38: =Comps!Q29 -> 15.783179 | H38: =I38-G38 -> 27.850305 | I38: =Comps!Q28 -> 43.633484
B39: Daily / Weekly | C39: Update USD/CAD exchange rate | D39: NAV Model → B25 | F39: Precedents: P/NAV | G39: =PTA!J26 -> 69.218145 | H39: =I39-G39 -> 38.935206 | I39: =PTA!J25 -> 108.15335
B40: Quarterly | C40: Update Balance Sheet (cash, leases, Gold Stream) | D40: Balance Sheet → Column B | F40: 52-Week Range | G40: 12.15 | H40: =I40-G40 -> 40.85 | I40: 53
B41: Quarterly | C41: Update shares outstanding (check for dilution) | D41: NAV Model → B29 | F41: Analyst Targets | G41: ='Broker Summary'!D9 -> 49 | H41: =I41-G41 -> 11 | I41: ='Broker Summary'!D5 -> 60
B42: As Needed | C42: Refresh commodity price scenarios (Bear/Base/Bull) | D42: Economic Assumptions → E4:I17
B43: As Needed | C43: Update "Last Updated" date on this page | D43: Cover Page → C7

Sheet Economic Assumptions
A1: ECONOMIC & FISCAL ASSUMPTIONS | F1: COMMODITY PRICE SCENARIOS
A2: Source: Eskay Creek NI 43-101 Updated Feasibility Study, December 22, 2023 | F2: Toggle scenario on NAV Model sheet (cell B14)
A3: Technical Report Link | F3: Prices updated as of: | G3: ='Cover Page'!C6 -> March 13, 2026
A5: BASE CASE ASSUMPTIONS | F5: GOLD PRICES (US$/oz) | H5: Bear | I5: Base | J5: Bull
A6: Parameter | B6: Units | C6: Value | D6: Relevance to NAV Model | F6: Year | G6: Period | H6: US$/oz | I6: US$/oz | J6: US$/oz
A7: Gold Price | B7: US$/oz | C7: =I10 -> 3150 | D7: Drives gross gold revenue; key sensitivity variable in NAV | F7: 2027 | G7: Near-term | H7: 4075 | I7: =AVERAGE(H7,J7) -> 5287.5 | J7: 6500
A8: Silver Price | B8: US$/oz | C8: =I17 -> 42 | D8: Drives silver by-product credits, reducing net cash costs | F8: 2028 | G8: Near-term | H8: 3675 | I8: =AVERAGE(H8,J8) -> 4837.5 | J8: 6000
A9: Exchange Rate (US$/C$) | B9: US$/C$ | C9: 0.74 | D9: Converts C$ costs to US$ for revenue/cost reconciliation | F9: 2029 | G9: Near-term | H9: 3425 | I9: =AVERAGE(H9,J9) -> 4462.5 | J9: 5500
A10: Discount Rate | B10: % | C10: 0.05 | D10: Taken as the project discount rate (5%) | F10: 2030+ | G10: Long-term | H10: 3000 | I10: =AVERAGE(H10,J10) -> 3150 | J10: 3300
A11: Royalty (NSR) | B11: % | C11: 0.02 | D11: Deducted from gross revenue to arrive at net revenue
A12: Strip Ratio (waste:ore) | B12: x | C12: 7.98:1 | D12: Impacts mining cost per tonne; higher ratio = more waste moved | F12: SILVER PRICES (US$/oz) | H12: Bear | I12: Base | J12: Bull
A13: Grams per Troy Ounce | B13: g/oz | C13: 31.1035 | D13: Converts grade (g/t) × tonnes to troy ounces for contained metal calculations | F13: Year | G13: Period | H13: US$/oz | I13: US$/oz | J13: US$/oz
A14: PRODUCTION & METALLURGY | F14: 2027 | G14: Near-term | H14: 49.5 | I14: 80 | J14: 120
A15: Parameter | B15: Units | C15: Value | D15: Relevance to NAV Model | F15: 2028 | G15: Near-term | H15: 45.25 | I15: 65 | J15: 105
A16: Processing Life | B16: years | C16: 12 | D16: Determines number of years of cash flows to discount | F16: 2029 | G16: Near-term | H16: 40.75 | I16: 55 | J16: 95
A17: Throughput (Years 1–5) | B17: Mtpa | C17: 3 | D17: Sets annual ore tonnage in early years → drives revenue timing | F17: 2030+ | G17: Long-term | H17: 33 | I17: 42 | J17: 70
A18: Throughput (Years 6–12) | B18: Mtpa | C18: 3.5 | D18: Sets annual ore tonnage in later years; higher throughput boosts output
A19: Avg Diluted Au Grade | B19: g/t | C19: 2.6 | D19: Multiplied by throughput and recovery to calculate gold ounces produced | F19: SOURCES
A20: Avg Diluted Ag Grade | B20: g/t | C20: 68.7 | D20: Multiplied by throughput and recovery to calculate silver ounces produced | F20: Bear | G20: BMO Capital Markets, as of December 15, 2025
A21: Gold Recovery (to concentrate) | B21: % | C21: 0.83 | D21: % of gold in ore recovered to concentrate; directly scales gold output | F21: Base | G21: Average of the two estimates (Au), and NBC Ag estimates as of February 2026
A22: Silver Recovery (to concentrate) | B22: % | C22: 0.91 | D22: % of silver in ore recovered to concentrate; scales silver by-product credit | F22: Bull | G22: CIBC Capital Markets, as of February 2, 2026
A23: LOM Gold Production | B23: koz | C23: 2769 | D23: Total gold ounces over mine life; basis for LOM revenue calculation
A24: LOM Silver Production | B24: koz | C24: 80052 | D24: Total silver ounces over mine life; drives cumulative by-product credits
A25: LOM AuEq Production | B25: koz | C25: 3891 | D25: Gold-equivalent total production; used for co-product cost metrics
A26: LOM Avg Annual Au Production | B26: koz/yr | C26: 228 | D26: Annual gold output benchmark; revenue run-rate indicator
A27: LOM average annual silver production (koz) | B27: koz/yr | C27: 6583 | D27: Annual silver output; feeds annual by-product credit calculation
A28: LOM Avg Annual AuEq Production | B28: koz/yr | C28: 320 | D28: Annual AuEq output; used to derive co-product cost per ounce
A30: CAPITAL EXPENDITURES
A31: Parameter | B31: Units | C31: Value | D31: Relevance to NAV Model
A32: Pre-Production Capex | B32: C$M | C32: 713 | D32: Upfront build cost; deducted from NAV as PV of remaining capex
A33: Expansion Capex | B33: C$M | C33: 9 | D33: One-time expansion spend; adds to total capex in year incurred
A34: Sustaining Capex | B34: C$M | C34: 561 | D34: Annual maintenance capex; included in AISC and deducted from FCF
A35: Closure Costs | B35: C$M | C35: 174.8 | D35: End-of-life reclamation cost; deducted from final-year FCF
A36: Initial Working Capital | B36: C$M | C36: 43.3 | D36: Pre-production ore stockpile; deducted from NAV as PV of working capital outflow

Sheet Models ->

Sheet NAV Model
B1: ESKAY CREEK — NAV MODEL
B2: Skeena Gold & Silver | Net Asset Value Analysis
B3: All figures in USD millions unless otherwise stated
A5: * | B5: KEY OUTPUTS
B6: NAV (US$ mm) | C6: =Q116 -> 6383.9423
B7: NAV per Share (US$) | C7: =Q117 -> 52.629368
B8: Current Share Price (US$) | C8: 31.46
B9: P/NAV Multiple | C9: =IF(C7=0,0,C8/C7) -> 0.59776511
B10: Mine Life (Years) | C10: ='Economic Assumptions'!C16 -> 12
B11: Total LOM Production (koz) | C11: =SUM(F62:Q62)/1000 -> 2723.6147
A13: * | B13: KEY ASSUMPTIONS
B14: ▶ Price Scenario | C14: Base
B15: 2027 Gold Price (US$/oz) | C15: =INDEX('Economic Assumptions'!H7:J7,MATCH(C14,{"Bear","Base","Bull"},0)) -> 5287.5
B16: 2028 Gold Price (US$/oz) | C16: =INDEX('Economic Assumptions'!H8:J8,MATCH(C14,{"Bear","Base","Bull"},0)) -> 4837.5
B17: 2029 Gold Price (US$/oz) | C17: =INDEX('Economic Assumptions'!H9:J9,MATCH(C14,{"Bear","Base","Bull"},0)) -> 4462.5
B18: LT Gold Price (US$/oz) | C18: =INDEX('Economic Assumptions'!H10:J10,MATCH(C14,{"Bear","Base","Bull"},0)) -> 3150
B19: 2027 Silver Price (US$/oz) | C19: =INDEX('Economic Assumptions'!H14:J14,MATCH(C14,{"Bear","Base","Bull"},0)) -> 80
B20: 2028 Silver Price (US$/oz) | C20: =INDEX('Economic Assumptions'!H15:J15,MATCH(C14,{"Bear","Base","Bull"},0)) -> 65
B21: 2029 Silver Price (US$/oz) | C21: =INDEX('Economic Assumptions'!H16:J16,MATCH(C14,{"Bear","Base","Bull"},0)) -> 55
B22: LT Silver Price (US$/oz) | C22: =INDEX('Economic Assumptions'!H17:J17,MATCH(C14,{"Bear","Base","Bull"},0)) -> 42
B23: Silver:Gold Ratio | C23: =IFERROR(C18/C22,0) -> 75
B24: USD/CAD Exchange Rate | C24: 1.37
B25: Discount Rate (WACC) | C25: ='Economic Assumptions'!C10 -> 0.05
B26: Royalty Rate (%) | C26: ='Economic Assumptions'!C11 -> 0.02
B27: Corporate Tax Rate (%) | C27: 0.27
B28: → Federal Income Tax | C28: 0.15
B29: → Provincial Income Tax (BC) | C29: 0.12
B30: BC Mineral Tax — NCP (net current proceeds) Rate (%) | C30: 0.02
B31: BC Mineral Tax — NRT (net revenue tax) Rate (%) | C31: 0.13
B32: Shares Outstanding (mm) | C32: 121.3
B33: Net Debt (negative = net cash) (US$ mm) | C33: =(61.7-108.2)/'Cover Page'!C15 -> -33.941606
B34: Depreciable Asset Base (US$ mm) | C34: ='Economic Assumptions'!C32/C24 -> 520.43796
B35: Pre-Production Capex (US$ mm) | C35: =C34 -> 520.43796
B36: Less: Already Spent (US$ mm) | C36: =437.742/'Cover Page'!C15 -> 319.51971
B37: Depreciation Method | C37: Units-of-Production
B38: Salvage Value (US$ mm) | C38: 0
B39: Closure Cost (US$ mm) | C39: ='Economic Assumptions'!C35/C24 -> 127.59124
B40: Initial Working Capital Adj. (US$ mm) | C40: ='Economic Assumptions'!C36/C24 -> 31.605839
B41: Additional M&I Conversion | C41: No
B42: Gold Stream Scenario | C42: None
B43: Stream Percentage (% of payable gold) | C43: 0.1055
B44: Orion Purchase Price (% of spot) | C44: 0.1
B45: Buyback Cost (US$ mm) | C45: 179
A47: * | B47: RESERVE & RESOURCE SUMMARY
B48: Category | C48: ='Reserve & Resource'!B4 -> Tonnes (000) | D48: Grade (g/t Au) | E48: Contained (koz)
B49: Proven Reserves | C49: ='Reserve & Resource'!B14 -> 27954 | D49: ='Reserve & Resource'!D14 -> 3 | E49: =C49*D49*1000/'Economic Assumptions'!$C$13/1000 -> 2696.2239
B50: Probable Reserves | C50: ='Reserve & Resource'!B15 -> 11889 | D50: ='Reserve & Resource'!D15 -> 1.8 | E50: =C50*D50*1000/'Economic Assumptions'!$C$13/1000 -> 688.03189
B51: Total P&P Reserves | C51: =SUM(C49:C50) -> 39843 | D51: =IF(C51=0,0,(E51*1000*31.1035)/(C51*1000)) -> 2.6419246 | E51: =SUM(E49:E50) -> 3384.2558
B52: M&I Resources (incl. Reserves) | C52: ='Reserve & Resource'!B5 -> 27814 | D52: ='Reserve & Resource'!D5 -> 3.3 | E52: =C52*D52*1000/'Economic Assumptions'!$C$13/1000 -> 2950.9927
B53: Inferred Resources | C53: ='Reserve & Resource'!B6 -> 22264 | D53: ='Reserve & Resource'!D6 -> 1.6 | E53: =C53*D53*1000/'Economic Assumptions'!$C$13/1000 -> 1145.2859
A55: * | B55: PRODUCTION PROFILE
C56: Units | D56: Total / Avg | E56: LOM Avg | F56: 2027 | G56: 2028 | H56: 2029 | I56: 2030 | J56: 2031 | K56: 2032 | L56: 2033 | M56: 2034 | N56: 2035 | O56: 2036 | P56: 2037 | Q56: 2038
B57: Ore Milled | C57: Mt | D57: =SUM(F57:Q57) -> 39.16 | E57: =D57/12 -> 3.2633333 | F57: ='Production Schedule'!F15 -> 2.96 | G57: ='Production Schedule'!G15 -> 3.01 | H57: ='Production Schedule'!H15 -> 3 | I57: ='Production Schedule'!I15 -> 3 | J57: ='Production Schedule'!J15 -> 3 | K57: ='Production Schedule'!K15 -> 3.51 | L57: ='Production Schedule'!L15 -> 3.5 | M57: ='Production Schedule'!M15 -> 3.5 | ... Q57: ='Production Schedule'!Q15 -> 3.17
B58: Additional M&I Ore Milled | C58: Mt | D58: =SUM(F58:Q58) -> 0 | E58: =D58/12 -> 0 | F58: =IF(C41="Yes",('Reserve & Resource'!B22/12/1000),0) -> 0 | G58: =F58 -> 0 | H58: =G58 -> 0 | I58: =H58 -> 0 | J58: =I58 -> 0 | K58: =J58 -> 0 | L58: =K58 -> 0 | M58: =L58 -> 0 | N58: =M58 -> 0 | ... Q58: =P58 -> 0
B59: Total Ore Milled | C59: Mt | D59: =SUM(F59:Q59) -> 39.16 | E59: =D59/12 -> 3.2633333 | F59: =SUM(F57:F58) -> 2.96 | G59: =SUM(G57:G58) -> 3.01 | H59: =SUM(H57:H58) -> 3 | I59: =SUM(I57:I58) -> 3 | J59: =SUM(J57:J58) -> 3 | K59: =SUM(K57:K58) -> 3.51 | L59: =SUM(L57:L58) -> 3.5 | M59: =SUM(M57:M58) -> 3.5 | ... Q59: =SUM(Q57:Q58) -> 3.17
B60: Head Grade | C60: g/t Au | E60: =IFERROR(AVERAGE(F60:Q60),0) -> 2.675 | F60: ='Production Schedule'!F16 -> 5 | G60: ='Production Schedule'!G16 -> 3.4 | H60: ='Production Schedule'!H16 -> 3.9 | I60: ='Production Schedule'!I16 -> 3.6 | J60: ='Production Schedule'!J16 -> 3.9 | K60: ='Production Schedule'!K16 -> 3.3 | L60: ='Production Schedule'!L16 -> 1.9 | M60: ='Production Schedule'!M16 -> 2.6 | ... Q60: ='Production Schedule'!Q16 -> 0.8
B61: Recovery Rate | C61: % | E61: =IFERROR(AVERAGE(F61:Q61),0) -> 0.83 | F61: ='Economic Assumptions'!$C$21 -> 0.83 | G61: ='Economic Assumptions'!$C$21 -> 0.83 | H61: ='Economic Assumptions'!$C$21 -> 0.83 | I61: ='Economic Assumptions'!$C$21 -> 0.83 | J61: ='Economic Assumptions'!$C$21 -> 0.83 | K61: ='Economic Assumptions'!$C$21 -> 0.83 | L61: ='Economic Assumptions'!$C$21 -> 0.83 | M61: ='Economic Assumptions'!$C$21 -> 0.83 | ... Q61: ='Economic Assumptions'!$C$21 -> 0.83
B62: Gold Produced | C62: oz | D62: =SUM(F62:Q62) -> 2723614.7 | E62: =D62/12 -> 226967.89 | F62: =F59*F60*F61*1000000/'Economic Assumptions'!$C$13 -> 394939.48 | G62: =G59*G60*G61*1000000/'Economic Assumptions'!$C$13 -> 273095.31 | H62: =H59*H60*H61*1000000/'Economic Assumptions'!$C$13 -> 312215.67 | I62: =I59*I60*I61*1000000/'Economic Assumptions'!$C$13 -> 288199.08 | J62: =J59*J60*J61*1000000/'Economic Assumptions'!$C$13 -> 312215.67 | K62: =K59*K60*K61*1000000/'Economic Assumptions'!$C$13 -> 309093.51 | L62: =L59*L60*L61*1000000/'Economic Assumptions'!$C$13 -> 177455.91 | M62: =M59*M60*M61*1000000/'Economic Assumptions'!$C$13 -> 242834.41 | ... Q62: =Q59*Q60*Q61*1000000/'Economic Assumptions'!$C$13 -> 67673.413
B63: Silver Grade | C63: g/t Ag | E63: =IFERROR(AVERAGE(F63:Q63),0) -> 70.866667 | F63: ='Production Schedule'!F17 -> 91.4 | G63: ='Production Schedule'!G17 -> 86 | H63: ='Production Schedule'!H17 -> 115.2 | I63: ='Production Schedule'!I17 -> 101.3 | J63: ='Production Schedule'!J17 -> 147.6 | K63: ='Production Schedule'!K17 -> 63 | L63: ='Production Schedule'!L17 -> 40.9 | M63: ='Production Schedule'!M17 -> 95.6 | ... Q63: ='Production Schedule'!Q17 -> 11.4
B64: Silver Recovery | C64: % | E64: =IFERROR(AVERAGE(F64:Q64),0) -> 0.91 | F64: ='Economic Assumptions'!$C$22 -> 0.91 | G64: ='Economic Assumptions'!$C$22 -> 0.91 | H64: ='Economic Assumptions'!$C$22 -> 0.91 | I64: ='Economic Assumptions'!$C$22 -> 0.91 | J64: ='Economic Assumptions'!$C$22 -> 0.91 | K64: ='Economic Assumptions'!$C$22 -> 0.91 | L64: ='Economic Assumptions'!$C$22 -> 0.91 | M64: ='Economic Assumptions'!$C$22 -> 0.91 | ... Q64: ='Economic Assumptions'!$C$22 -> 0.91
B65: Silver Produced | C65: oz | D65: =SUM(F65:Q65) -> 78993097 | E65: =D65/12 -> 6582758 | F65: =F59*F63*F64*1000000/'Economic Assumptions'!$C$13 -> 7915348.4 | G65: =G59*G63*G64*1000000/'Economic Assumptions'!$C$13 -> 7573507.8 | H65: =H59*H63*H64*1000000/'Economic Assumptions'!$C$13 -> 10111274 | I65: =I59*I63*I64*1000000/'Economic Assumptions'!$C$13 -> 8891250.2 | J65: =J59*J63*J64*1000000/'Economic Assumptions'!$C$13 -> 12955069 | K65: =K59*K63*K64*1000000/'Economic Assumptions'!$C$13 -> 6469635.3 | L65: =L59*L63*L64*1000000/'Economic Assumptions'!$C$13 -> 4188162.1 | M65: =M59*M63*M64*1000000/'Economic Assumptions'!$C$13 -> 9789444.9 | ... Q65: =Q59*Q63*Q64*1000000/'Economic Assumptions'!$C$13 -> 1057295.2
A67: * | B67: REVENUE
B68: Gold Price | C68: US$/oz | E68: =IFERROR(AVERAGE(F68:Q68),0) -> 3578.125 | F68: =C15 -> 5287.5 | G68: =C16 -> 4837.5 | H68: =C17 -> 4462.5 | I68: =$C$18 -> 3150 | J68: =$C$18 -> 3150 | K68: =$C$18 -> 3150 | L68: =$C$18 -> 3150 | M68: =$C$18 -> 3150 | N68: =$C$18 -> 3150 | O68: =$C$18 -> 3150 | P68: =$C$18 -> 3150 | Q68: =$C$18 -> 3150
B69: Silver Price | C69: US$/oz | E69: =IFERROR(AVERAGE(F69:Q69),0) -> 48.166667 | F69: =C19 -> 80 | G69: =C20 -> 65 | H69: =C21 -> 55 | I69: =$C$22 -> 42 | J69: =$C$22 -> 42 | K69: =$C$22 -> 42 | L69: =$C$22 -> 42 | M69: =$C$22 -> 42 | N69: =$C$22 -> 42 | O69: =$C$22 -> 42 | P69: =$C$22 -> 42 | Q69: =$C$22 -> 42
B70: Gross Revenue | C70: US$ mm | D70: =SUM(F70:Q70) -> 10294.201 | E70: =D70/12 -> 857.85007 | F70: =F62*F68/1000000 -> 2088.2425 | G70: =G62*G68/1000000 -> 1321.0986 | H70: =H62*H68/1000000 -> 1393.2624 | I70: =I62*I68/1000000 -> 907.82709 | J70: =J62*J68/1000000 -> 983.47935 | K70: =K62*K68/1000000 -> 973.64456 | L70: =L62*L68/1000000 -> 558.98613 | M70: =M62*M68/1000000 -> 764.92838 | ... Q70: =Q62*Q68/1000000 -> 213.17125
B71: Royalty | C71: US$ mm | D71: =SUM(F71:Q71) -> 205.88402 | E71: =D71/12 -> 17.157001 | F71: =F70*$C$26 -> 41.76485 | G71: =G70*$C$26 -> 26.421971 | H71: =H70*$C$26 -> 27.865248 | I71: =I70*$C$26 -> 18.156542 | J71: =J70*$C$26 -> 19.669587 | K71: =K70*$C$26 -> 19.472891 | L71: =L70*$C$26 -> 11.179723 | M71: =M70*$C$26 -> 15.298568 | ... Q71: =Q70*$C$26 -> 4.263425
B72: Gold Stream Delivery (at spot) | C72: US$ mm | D72: =SUM(F72:Q72) -> 0 | E72: =D72/12 -> 0 | F72: =IF($C$42="None",0,IF($C$42="Buyback",$C$43*(1-0.6667),$C$43))*F62*F68/1000000 -> 0 | G72: =IF($C$42="None",0,IF($C$42="Buyback",$C$43*(1-0.6667),$C$43))*G62*G68/1000000 -> 0 | H72: =IF($C$42="None",0,IF($C$42="Buyback",$C$43*(1-0.6667),$C$43))*H62*H68/1000000 -> 0 | I72: =IF($C$42="None",0,IF($C$42="Buyback",$C$43*(1-0.6667),$C$43))*I62*I68/1000000 -> 0 | J72: =IF($C$42="None",0,IF($C$42="Buyback",$C$43*(1-0.6667),$C$43))*J62*J68/1000000 -> 0 | K72: =IF($C$42="None",0,IF($C$42="Buyback",$C$43*(1-0.6667),$C$43))*K62*K68/1000000 -> 0 | L72: =IF($C$42="None",0,IF($C$42="Buyback",$C$43*(1-0.6667),$C$43))*L62*L68/1000000 -> 0 | M72: =IF($C$42="None",0,IF($C$42="Buyback",$C$43*(1-0.6667),$C$43))*M62*M68/1000000 -> 0 | ... Q72: =IF($C$42="None",0,IF($C$42="Buyback",$C$43*(1-0.6667),$C$43))*Q62*Q68/1000000 -> 0
B73: Less: Orion Payment Received | C73: US$ mm | D73: =SUM(F73:Q73) -> 0 | E73: =D73/12 -> 0 | F73: =-IF($C$42="None",0,IF($C$42="Buyback",$C$43*(1-0.6667),$C$43))*F62*F68*$C$44/1000000 -> 0 | G73: =-IF($C$42="None",0,IF($C$42="Buyback",$C$43*(1-0.6667),$C$43))*G62*G68*$C$44/1000000 -> 0 | H73: =-IF($C$42="None",0,IF($C$42="Buyback",$C$43*(1-0.6667),$C$43))*H62*H68*$C$44/1000000 -> 0 | I73: =-IF($C$42="None",0,IF($C$42="Buyback",$C$43*(1-0.6667),$C$43))*I62*I68*$C$44/1000000 -> 0 | J73: =-IF($C$42="None",0,IF($C$42="Buyback",$C$43*(1-0.6667),$C$43))*J62*J68*$C$44/1000000 -> 0 | K73: =-IF($C$42="None",0,IF($C$42="Buyback",$C$43*(1-0.6667),$C$43))*K62*K68*$C$44/1000000 -> 0 | L73: =-IF($C$42="None",0,IF($C$42="Buyback",$C$43*(1-0.6667),$C$43))*L62*L68*$C$44/1000000 -> 0 | M73: =-IF($C$42="None",0,IF($C$42="Buyback",$C$43*(1-0.6667),$C$43))*M62*M68*$C$44/1000000 -> 0 | ... Q73: =-IF($C$42="None",0,IF($C$42="Buyback",$C$43*(1-0.6667),$C$43))*Q62*Q68*$C$44/1000000 -> 0
B74: Net Revenue | C74: US$ mm | D74: =SUM(F74:Q74) -> 10088.317 | E74: =D74/12 -> 840.69307 | F74: =F70-F71-F72-F73 -> 2046.4776 | G74: =G70-G71-G72-G73 -> 1294.6766 | H74: =H70-H71-H72-H73 -> 1365.3972 | I74: =I70-I71-I72-I73 -> 889.67055 | J74: =J70-J71-J72-J73 -> 963.80976 | K74: =K70-K71-K72-K73 -> 954.17167 | L74: =L70-L71-L72-L73 -> 547.8064 | M74: =M70-M71-M72-M73 -> 749.62982 | ... Q74: =Q70-Q71-Q72-Q73 -> 208.90783
A75: * | B75: OPERATING COSTS
B76: Mining Cost | C76: US$/oz | E76: =IFERROR(AVERAGE(F76:Q76),0) -> 300.81762 | F76: =IFERROR(IF(F56<=2031,'Operating Costs'!$C$6,'Operating Costs'!$E$6)*F57*1000000/F62/$C$24,0) -> 248.36846 | G76: =IFERROR(IF(G56<=2031,'Operating Costs'!$C$6,'Operating Costs'!$E$6)*G57*1000000/G62/$C$24,0) -> 365.24774 | H76: =IFERROR(IF(H56<=2031,'Operating Costs'!$C$6,'Operating Costs'!$E$6)*H57*1000000/H62/$C$24,0) -> 318.42111 | I76: =IFERROR(IF(I56<=2031,'Operating Costs'!$C$6,'Operating Costs'!$E$6)*I57*1000000/I62/$C$24,0) -> 344.9562 | J76: =IFERROR(IF(J56<=2031,'Operating Costs'!$C$6,'Operating Costs'!$E$6)*J57*1000000/J62/$C$24,0) -> 318.42111 | K76: =IFERROR(IF(K56<=2031,'Operating Costs'!$C$6,'Operating Costs'!$E$6)*K57*1000000/K62/$C$24,0) -> 118.86276 | L76: =IFERROR(IF(L56<=2031,'Operating Costs'!$C$6,'Operating Costs'!$E$6)*L57*1000000/L62/$C$24,0) -> 206.44585 | M76: =IFERROR(IF(M56<=2031,'Operating Costs'!$C$6,'Operating Costs'!$E$6)*M57*1000000/M62/$C$24,0) -> 150.86427 | ... Q76: =IFERROR(IF(Q56<=2031,'Operating Costs'!$C$6,'Operating Costs'!$E$6)*Q57*1000000/Q62/$C$24,0) -> 490.30889
B77: Processing Cost | C77: US$/oz | E77: =IFERROR(AVERAGE(F77:Q77),0) -> 276.39134 | F77: =IFERROR(IF(F56<=2031,'Operating Costs'!$C$7,'Operating Costs'!$E$7)*F57*1000000/F62/$C$24,0) -> 109.57754 | G77: =IFERROR(IF(G56<=2031,'Operating Costs'!$C$7,'Operating Costs'!$E$7)*G57*1000000/G62/$C$24,0) -> 161.14344 | H77: =IFERROR(IF(H56<=2031,'Operating Costs'!$C$7,'Operating Costs'!$E$7)*H57*1000000/H62/$C$24,0) -> 140.48403 | I77: =IFERROR(IF(I56<=2031,'Operating Costs'!$C$7,'Operating Costs'!$E$7)*I57*1000000/I62/$C$24,0) -> 152.19103 | J77: =IFERROR(IF(J56<=2031,'Operating Costs'!$C$7,'Operating Costs'!$E$7)*J57*1000000/J62/$C$24,0) -> 140.48403 | K77: =IFERROR(IF(K56<=2031,'Operating Costs'!$C$7,'Operating Costs'!$E$7)*K57*1000000/K62/$C$24,0) -> 154.17346 | L77: =IFERROR(IF(L56<=2031,'Operating Costs'!$C$7,'Operating Costs'!$E$7)*L57*1000000/L62/$C$24,0) -> 267.77495 | M77: =IFERROR(IF(M56<=2031,'Operating Costs'!$C$7,'Operating Costs'!$E$7)*M57*1000000/M62/$C$24,0) -> 195.68169 | ... Q77: =IFERROR(IF(Q56<=2031,'Operating Costs'!$C$7,'Operating Costs'!$E$7)*Q57*1000000/Q62/$C$24,0) -> 635.9655
B78: G&A & Water Treatment | C78: US$/oz | E78: =IFERROR(AVERAGE(F78:Q78),0) -> 113.30463 | F78: =IFERROR(IF(F56<=2031,'Operating Costs'!$C$8,'Operating Costs'!$E$8)*F57*1000000/F62/$C$24,0) -> 52.463735 | G78: =IFERROR(IF(G56<=2031,'Operating Costs'!$C$8,'Operating Costs'!$E$8)*G57*1000000/G62/$C$24,0) -> 77.152551 | H78: =IFERROR(IF(H56<=2031,'Operating Costs'!$C$8,'Operating Costs'!$E$8)*H57*1000000/H62/$C$24,0) -> 67.261199 | I78: =IFERROR(IF(I56<=2031,'Operating Costs'!$C$8,'Operating Costs'!$E$8)*I57*1000000/I62/$C$24,0) -> 72.866299 | J78: =IFERROR(IF(J56<=2031,'Operating Costs'!$C$8,'Operating Costs'!$E$8)*J57*1000000/J62/$C$24,0) -> 67.261199 | K78: =IFERROR(IF(K56<=2031,'Operating Costs'!$C$8,'Operating Costs'!$E$8)*K57*1000000/K62/$C$24,0) -> 60.343159 | L78: =IFERROR(IF(L56<=2031,'Operating Costs'!$C$8,'Operating Costs'!$E$8)*L57*1000000/L62/$C$24,0) -> 104.80654 | M78: =IFERROR(IF(M56<=2031,'Operating Costs'!$C$8,'Operating Costs'!$E$8)*M57*1000000/M62/$C$24,0) -> 76.589394 | ... Q78: =IFERROR(IF(Q56<=2031,'Operating Costs'!$C$8,'Operating Costs'!$E$8)*Q57*1000000/Q62/$C$24,0) -> 248.91553
B79: Less: Silver By-Product Credit | C79: US$/oz Au | E79: =IFERROR(AVERAGE(F79:Q79),0) -> -1315.3093 | F79: =IFERROR(-F65*F69/F62,0) -> -1603.3542 | G79: =IFERROR(-G65*G69/G62,0) -> -1802.5868 | H79: =IFERROR(-H65*H69/H62,0) -> -1781.2048 | I79: =IFERROR(-I65*I69/I62,0) -> -1295.745 | J79: =IFERROR(-J65*J69/J62,0) -> -1742.747 | K79: =IFERROR(-K65*K69/K62,0) -> -879.10186 | L79: =IFERROR(-L65*L69/L62,0) -> -991.24794 | M79: =IFERROR(-M65*M69/M62,0) -> -1693.1566 | ... Q79: =IFERROR(-Q65*Q69/Q62,0) -> -656.18675
B80: Total Cash Cost | C80: US$/oz | E80: =IFERROR(AVERAGE(F80:Q80),0) -> -624.79575 | F80: =SUM(F76:F79) -> -1192.9445 | G80: =SUM(G76:G79) -> -1199.0431 | H80: =SUM(H76:H79) -> -1255.0385 | I80: =SUM(I76:I79) -> -725.73145 | J80: =SUM(J76:J79) -> -1216.5807 | K80: =SUM(K76:K79) -> -545.72249 | L80: =SUM(L76:L79) -> -412.2206 | M80: =SUM(M76:M79) -> -1270.0213 | ... Q80: =SUM(Q76:Q79) -> 719.00318
B81: Total Opex | C81: US$ mm | D81: =SUM(F81:Q81) -> -2394.2245 | E81: =D81/12 -> -199.51871 | F81: =F80*F62/1000000 -> -471.14087 | G81: =G80*G62/1000000 -> -327.45304 | H81: =H80*H62/1000000 -> -391.84268 | I81: =I80*I62/1000000 -> -209.15514 | J81: =J80*J62/1000000 -> -379.83554 | K81: =K80*K62/1000000 -> -168.67928 | L81: =L80*L62/1000000 -> -73.150984 | M81: =M80*M62/1000000 -> -308.40486 | ... Q81: =Q80*Q62/1000000 -> 48.657399
B82: Cash Margin | C82: % | E82: =IFERROR(AVERAGE(F82:Q82),0) -> 1.1647591 | F82: =IF(F70=0,0,1-F81/F70) -> 1.225616 | G82: =IF(G70=0,0,1-G81/G70) -> 1.2478642 | H82: =IF(H70=0,0,1-H81/H70) -> 1.2812411 | I82: =IF(I70=0,0,1-I81/I70) -> 1.2303909 | J82: =IF(J70=0,0,1-J81/J70) -> 1.3862161 | K82: =IF(K70=0,0,1-K81/K70) -> 1.1732452 | L82: =IF(L70=0,0,1-L81/L70) -> 1.1308637 | M82: =IF(M70=0,0,1-M81/M70) -> 1.4031814 | ... Q82: =IF(Q70=0,0,1-Q81/Q70) -> 0.77174502
A84: * | B84: CAPITAL EXPENDITURE
B85: Sustaining Capex | C85: US$ mm | D85: =SUM(F85:Q85) -> 409.70803 | E85: =D85/12 -> 34.142336 | F85: ='Capital Costs'!C16/12/$C$24 -> 34.142336 | G85: ='Capital Costs'!C16/12/$C$24 -> 34.142336 | H85: ='Capital Costs'!C16/12/$C$24 -> 34.142336 | I85: ='Capital Costs'!C16/12/$C$24 -> 34.142336 | J85: ='Capital Costs'!C16/12/$C$24 -> 34.142336 | K85: ='Capital Costs'!C16/12/$C$24 -> 34.142336 | L85: ='Capital Costs'!C16/12/$C$24 -> 34.142336 | M85: ='Capital Costs'!C16/12/$C$24 -> 34.142336 | N85: ='Capital Costs'!C16/12/$C$24 -> 34.142336 | O85: ='Capital Costs'!C16/12/$C$24 -> 34.142336 | P85: ='Capital Costs'!C16/12/$C$24 -> 34.142336 | Q85: ='Capital Costs'!C16/12/$C$24 -> 34.142336
B86: Growth / Expansion Capex | C86: US$ mm | D86: =SUM(F86:Q86) -> 6.350365 | E86: =D86/12 -> 0.52919708 | F86: 0 | G86: 0 | H86: 0 | I86: 0 | J86: 0 | K86: ='Capital Costs'!D16/$C$24 -> 6.350365 | L86: 0 | M86: 0 | N86: 0 | O86: 0 | P86: 0 | Q86: 0
B87: Closure / Rehab Capex | C87: US$ mm | D87: =SUM(F87:Q87) -> 127.59124 | E87: =D87/12 -> 10.632603 | F87: 0 | G87: 0 | H87: 0 | I87: 0 | J87: 0 | K87: 0 | L87: 0 | M87: 0 | N87: 0 | O87: 0 | P87: 0 | Q87: ='Capital Costs'!E16/$C$24 -> 127.59124
B88: Total Capex | C88: US$ mm | D88: =SUM(F88:Q88) -> 543.64964 | E88: =D88/12 -> 45.304136 | F88: =SUM(F85:F87) -> 34.142336 | G88: =SUM(G85:G87) -> 34.142336 | H88: =SUM(H85:H87) -> 34.142336 | I88: =SUM(I85:I87) -> 34.142336 | J88: =SUM(J85:J87) -> 34.142336 | K88: =SUM(K85:K87) -> 40.492701 | L88: =SUM(L85:L87) -> 34.142336 | M88: =SUM(M85:M87) -> 34.142336 | ... Q88: =SUM(Q85:Q87) -> 161.73358
B89: AISC per oz | C89: US$/oz | E89: =IFERROR((D81+D71+D85)*1000000/D62,0) -> -653.04116 | F89: =IFERROR(F80+(F71+F85)*1000000/F62,0) -> -1000.7449 | G89: =IFERROR(G80+(G71+G85)*1000000/G62,0) -> -977.27323 | H89: =IFERROR(H80+(H71+H85)*1000000/H62,0) -> -1056.4335 | I89: =IFERROR(I80+(I71+I85)*1000000/I62,0) -> -544.26357 | J89: =IFERROR(J80+(J71+J85)*1000000/J62,0) -> -1044.2257 | K89: =IFERROR(K80+(K71+K85)*1000000/K62,0) -> -372.26292 | L89: =IFERROR(L80+(L71+L85)*1000000/L62,0) -> -156.82163 | M89: =IFERROR(M80+(M71+M85)*1000000/M62,0) -> -1066.422 | ... Q89: =IFERROR(Q80+(Q71+Q85)*1000000/Q62,0) -> 1286.5194
B90: AISC (excl. Silver Credit) | C90: US$/oz | E90: =IFERROR(AVERAGE(F90:Q90),0) -> 968.10665 | F90: =F89-F79 -> 602.60928 | G90: =G89-G79 -> 825.31359 | H90: =H89-H79 -> 724.7713 | I90: =I89-I79 -> 751.48141 | J90: =J89-J79 -> 698.5213 | K90: =K89-K79 -> 506.83894 | L90: =L89-L79 -> 834.42631 | M90: =M89-M79 -> 626.73461 | ... Q90: =Q89-Q79 -> 1942.7062
A91: * | B91: TAX & DEPRECIATION
B92: EBITDA | C92: US$ mm | D92: =SUM(F92:Q92) -> 12482.541 | E92: =D92/12 -> 1040.2118 | F92: =F74-F81 -> 2517.6185 | G92: =G74-G81 -> 1622.1296 | H92: =H74-H81 -> 1757.2398 | I92: =I74-I81 -> 1098.8257 | J92: =J74-J81 -> 1343.6453 | K92: =K74-K81 -> 1122.8509 | L92: =L74-L81 -> 620.95739 | M92: =M74-M81 -> 1058.0347 | ... Q92: =Q74-Q81 -> 160.25043
B93: Depreciation (UoP) | C93: US$ mm | D93: =SUM(F93:Q93) -> 520.43796 | E93: =D93/12 -> 43.36983 | F93: =IF($C$34="",0,($C$34-$C$38)*(F62/$D$62)) -> 75.466436 | G93: =IF($C$34="",0,($C$34-$C$38)*(G62/$D$62)) -> 52.18402 | H93: =IF($C$34="",0,($C$34-$C$38)*(H62/$D$62)) -> 59.659277 | I93: =IF($C$34="",0,($C$34-$C$38)*(I62/$D$62)) -> 55.070102 | J93: =IF($C$34="",0,($C$34-$C$38)*(J62/$D$62)) -> 59.659277 | K93: =IF($C$34="",0,($C$34-$C$38)*(K62/$D$62)) -> 59.062684 | L93: =IF($C$34="",0,($C$34-$C$38)*(L62/$D$62)) -> 33.908905 | M93: =IF($C$34="",0,($C$34-$C$38)*(M62/$D$62)) -> 46.40166 | ... Q93: =IF($C$34="",0,($C$34-$C$38)*(Q62/$D$62)) -> 12.931276
B94: BC MINERAL TAX
B95: NCP Base (Net Rev − Opex) | C95: US$ mm | D95: =SUM(F95:Q95) -> 12482.541 | E95: =D95/12 -> 1040.2118 | F95: =MAX(0,F74-F81) -> 2517.6185 | G95: =MAX(0,G74-G81) -> 1622.1296 | H95: =MAX(0,H74-H81) -> 1757.2398 | I95: =MAX(0,I74-I81) -> 1098.8257 | J95: =MAX(0,J74-J81) -> 1343.6453 | K95: =MAX(0,K74-K81) -> 1122.8509 | L95: =MAX(0,L74-L81) -> 620.95739 | M95: =MAX(0,M74-M81) -> 1058.0347 | ... Q95: =MAX(0,Q74-Q81) -> 160.25043
B96: NCP Tax (2%) | C96: US$ mm | D96: =SUM(F96:Q96) -> 249.65083 | E96: =D96/12 -> 20.804236 | F96: =F95*$C$30 -> 50.35237 | G96: =G95*$C$30 -> 32.442593 | H96: =H95*$C$30 -> 35.144797 | I96: =I95*$C$30 -> 21.976514 | J96: =J95*$C$30 -> 26.872906 | K96: =K95*$C$30 -> 22.457019 | L96: =L95*$C$30 -> 12.419148 | M96: =M95*$C$30 -> 21.160694 | ... Q96: =Q95*$C$30 -> 3.2050085
B97: NRT Base (NCP Base − Depr.) | C97: US$ mm | D97: =SUM(F97:Q97) -> 11962.103 | E97: =D97/12 -> 996.84195 | F97: =MAX(0,F95-F93) -> 2442.1521 | G97: =MAX(0,G95-G93) -> 1569.9456 | H97: =MAX(0,H95-H93) -> 1697.5806 | I97: =MAX(0,I95-I93) -> 1043.7556 | J97: =MAX(0,J95-J93) -> 1283.986 | K97: =MAX(0,K95-K93) -> 1063.7883 | L97: =MAX(0,L95-L93) -> 587.04848 | M97: =MAX(0,M95-M93) -> 1011.633 | ... Q97: =MAX(0,Q95-Q93) -> 147.31915
B98: NRT Tax (13%) | C98: US$ mm | D98: =SUM(F98:Q98) -> 1555.0734 | E98: =D98/12 -> 129.58945 | F98: =F97*$C$31 -> 317.47977 | G98: =G97*$C$31 -> 204.09293 | H98: =H97*$C$31 -> 220.68547 | I98: =I97*$C$31 -> 135.68823 | J98: =J97*$C$31 -> 166.91818 | K98: =K97*$C$31 -> 138.29247 | L98: =L97*$C$31 -> 76.316303 | M98: =M97*$C$31 -> 131.51229 | ... Q98: =Q97*$C$31 -> 19.15149
B99: BC Mineral Tax (higher of NCP / NRT) | C99: $ mm | D99: =SUM(F99:Q99) -> 1555.0734 | E99: =D99/12 -> 129.58945 | F99: =MAX(F96,F98) -> 317.47977 | G99: =MAX(G96,G98) -> 204.09293 | H99: =MAX(H96,H98) -> 220.68547 | I99: =MAX(I96,I98) -> 135.68823 | J99: =MAX(J96,J98) -> 166.91818 | K99: =MAX(K96,K98) -> 138.29247 | L99: =MAX(L96,L98) -> 76.316303 | M99: =MAX(M96,M98) -> 131.51229 | ... Q99: =MAX(Q96,Q98) -> 19.15149
B100: CORPORATE INCOME TAX
B101: Corporate Taxable Income | C101: US$ mm | D101: =SUM(F101:Q101) -> 10407.03 | E101: =D101/12 -> 867.2525 | F101: =MAX(0,F92-F93-F99) -> 2124.6723 | G101: =MAX(0,G92-G93-G99) -> 1365.8527 | H101: =MAX(0,H92-H93-H99) -> 1476.8951 | I101: =MAX(0,I92-I93-I99) -> 908.06736 | J101: =MAX(0,J92-J93-J99) -> 1117.0678 | K101: =MAX(0,K92-K93-K99) -> 925.49579 | L101: =MAX(0,L92-L93-L99) -> 510.73218 | M101: =MAX(0,M92-M93-M99) -> 880.12073 | ... Q101: =MAX(0,Q92-Q93-Q99) -> 128.16766
B102: Corporate Income Tax | C102: US$ mm | D102: =SUM(F102:Q102) -> 2809.8981 | E102: =D102/12 -> 234.15817 | F102: =F101*$C$27 -> 573.66152 | G102: =G101*$C$27 -> 368.78023 | H102: =H101*$C$27 -> 398.76168 | I102: =I101*$C$27 -> 245.17819 | J102: =J101*$C$27 -> 301.60832 | K102: =K101*$C$27 -> 249.88386 | L102: =L101*$C$27 -> 137.89769 | M102: =M101*$C$27 -> 237.6326 | ... Q102: =Q101*$C$27 -> 34.605269
B103: Total Tax Payable | C103: US$ mm | D103: =SUM(F103:Q103) -> 4364.9715 | E103: =D103/12 -> 363.74763 | F103: =F99+F102 -> 891.14129 | G103: =G99+G102 -> 572.87316 | H103: =H99+H102 -> 619.44715 | I103: =I99+I102 -> 380.86641 | J103: =J99+J102 -> 468.5265 | K103: =K99+K102 -> 388.17634 | L103: =L99+L102 -> 214.21399 | M103: =M99+M102 -> 369.14489 | ... Q103: =Q99+Q102 -> 53.756758
B104: Effective Tax Rate | C104: % | D104: =IFERROR(D103/D92,0) -> 0.34968613 | E104: =IFERROR(E103/E92,0) -> 0.34968613 | F104: =IFERROR(F103/F92,0) -> 0.353962 | G104: =IFERROR(G103/G92,0) -> 0.35316114 | H104: =IFERROR(H103/H92,0) -> 0.35251144 | I104: =IFERROR(I103/I92,0) -> 0.34661222 | J104: =IFERROR(J103/J92,0) -> 0.34869805 | K104: =IFERROR(K103/K92,0) -> 0.34570602 | ... Q104: =IFERROR(Q103/Q92,0) -> 0.3354547
A105: * | B105: FREE CASH FLOW & NAV
B106: Unlevered FCF | C106: US$ mm | D106: =SUM(F106:Q106) -> 7573.9202 | E106: =D106/12 -> 631.16002 | F106: =F92-F103-F88 -> 1592.3349 | G106: =G92-G103-G88 -> 1015.1141 | H106: =H92-H103-H88 -> 1103.6504 | I106: =I92-I103-I88 -> 683.81694 | J106: =J92-J103-J88 -> 840.97647 | K106: =K92-K103-K88 -> 694.18191 | L106: =L92-L103-L88 -> 372.60106 | M106: =M92-M103-M88 -> 654.74745 | ... Q106: =Q92-Q103-Q88 -> -55.239908
...

Sheet Comps
B2: SELECTED PUBLIC MARKET COMPARABLES ¹
B4: DATA FRESHNESS
B5: Comps Last Updated | C5: 46094 | D5: ← Update this date when refreshing comps
B6: Current Share Price | C6: ='NAV Model'!C8*'NAV Model'!$C$24 -> 43.1002
B8: Description | N8: Valuation
B9: Company | C9: Ticker | D9: Domicile | E9: Share Price (LC) | F9: Market Cap ($mm LC) | G9: EV ($mm LC) | H9: Reserves (kozAuEq) | I9: Resources (kozAuEq) | J9: Shares Outstanding (mm) | K9: NAV | L9: EBITDA ($mm LC) | N9: NAV | P9: EV/Materials (LC/kozAuEq) | R9: EV/EBITDA
L10: 2026E | M10: 2027E | N10: /share (LC) | O10: P/NAV | P10: EV/Reserves | Q10: EV/Resources | R10: 2026E | S10: 2027E
A11: Development | B11: Bellevue Gold | C11: BGL | D11: Australia | E11: 1.615 | F11: 2391.4 | G11: 2566 | H11: =1.29*1000 -> 1290 | I11: =3.1*1000 -> 3100 | J11: 1480.7 | K11: =F11/0.86 -> 2780.6977 | L11: 402.9 | M11: 591.1 | N11: =K11/J11 -> 1.8779616 | O11: =F11/K11 -> 0.86 | P11: =$G11/H11 -> 1.9891473 | Q11: =$G11/I11 -> 0.82774194 | R11: =$G11/L11 -> 6.368826 | S11: =$G11/M11 -> 4.341059 | U11: Potential comps
A12: Stage | B12: Rupert Resources | C12: RUP | D12: Canada | E12: 7.52 | F12: 1770.2 | G12: 1684.4 | H12: =3.5*1000 -> 3500 | I12: =5*1000 -> 5000 | J12: 235.4 | K12: =F12/0.33 -> 5364.2424 | L12: N/A | M12: N/A | N12: =K12/J12 -> 22.787776 | O12: =F12/K12 -> 0.33 | P12: =$G12/H12 -> 0.48125714 | Q12: =$G12/I12 -> 0.33688 | R12: N/A | S12: N/A | U12: Bellevue Gold | W12: yes
B13: G Mining Ventures | C13: GMIN | D13: Canada | E13: 51.48 | F13: 8648.2 | G13: 8671.2 | H13: 6516 | I13: 9165 | J13: 228.2 | K13: =F13/0.8 -> 10810.25 | L13: 432.8 | M13: 595.2 | N13: =K13/J13 -> 47.371823 | O13: =F13/K13 -> 0.8 | P13: =$G13/H13 -> 1.3307551 | Q13: =$G13/I13 -> 0.94612111 | R13: =$G13/L13 -> 20.03512 | S13: =$G13/M13 -> 14.568548 | U13: G Mining Ventures | W13: maybe - BRA jurisdiciton but similar stage
A14: Single-Asset | B14: Lundin Gold | C14: LUG | D14: Canada | E14: 112.18 | F14: 27098.3 | G14: 19339.7 | H14: 5845 | I14: 7480 | J14: 241.7 | K14: =F14/1.1 -> 24634.818 | L14: 1792.5 | M14: 1868.7 | N14: =K14/J14 -> 101.92312 | O14: =F14/K14 -> 1.1 | P14: Ignored since materially higher post-production | R14: =$G14/L14 -> 10.789233 | S14: =$G14/M14 -> 10.34928
A15: Producers | B15: K92 Mining | C15: KNT | D15: Canada | E15: 27.67 | F15: 4967.7 | G15: 4842 | H15: =1.69*1000 -> 1690 | I15: =2600 -> 2600 | J15: 243.9 | K15: =F15/0.56 -> 8870.8929 | L15: 664.7 | M15: 994 | N15: =K15/J15 -> 36.371024 | O15: =F15/K15 -> 0.56 | R15: =$G15/L15 -> 7.2844892 | S15: =$G15/M15 -> 4.8712274
B16: Wesdome Gold | C16: WDO | D16: Canada | E16: 23.42 | F16: 3521.9 | G16: 3237.2 | H16: 1188 | I16: =H16+386 -> 1574 | J16: 150.4 | K16: =F16/1.12 -> 3144.5536 | L16: 601 | M16: 936 | N16: =K16/J16 -> 20.907936 | O16: =F16/K16 -> 1.12 | R16: =$G16/L16 -> 5.3863561 | S16: =$G16/M16 -> 3.458547 | U16: Lundin Gold | W16: Similar mine but alr producing in Ecuador
U17: K92 Mining | W17: Similar mine but alr producing in PNG
B18: Skeena Resources | C18: SKE | D18: Canada | E18: =C6 -> 43.1002 | F18: =E18*J18 -> 5228.0543 | G18: =F18+'NAV Model'!C33*'NAV Model'!$C$24 -> 5181.5543 | H18: ='Reserve & Resource'!F16 -> 4569 | I18: ='Reserve & Resource'!F7 -> 5545 | J18: ='NAV Model'!C32 -> 121.3 | K18: ='Cover Page'!G12*'NAV Model'!$C$24 -> 8746.001 | L18: N/A | M18: 687.9 | N18: =K18/J18 -> 72.102234 | O18: =F18/K18 -> 0.59776511 | P18: =$G18/H18 -> 1.1340675 | Q18: =$G18/I18 -> 0.93445523 | R18: N/A | S18: =$G18/M18 -> 7.5324237 | U18: Wesdome Gold | W18: 2 mines in CAD both producing
B19: Junior Gold | U19: Rupert Resources | W19: yes
B20: Mean | O20: =AVERAGE(O11:O16) -> 0.795 | P20: =AVERAGE(P11:P16) -> 1.2670532 | Q20: =AVERAGE(Q11:Q16) -> 0.70358102 | R20: =AVERAGE(R11:R16) -> 9.9728049 | S20: =AVERAGE(S11:S16) -> 7.5177324
B21: Median | O21: =MEDIAN(O11:O16) -> 0.83 | P21: =MEDIAN(P11:P16) -> 1.3307551 | Q21: =MEDIAN(Q11:Q16) -> 0.82774194 | R21: =MEDIAN(R11:R16) -> 7.2844892 | S21: =MEDIAN(S11:S16) -> 4.8712274
B22: High | O22: =MAX(O11:O16) -> 1.12 | P22: =MAX(P11:P16) -> 1.9891473 | Q22: =MAX(Q11:Q16) -> 0.94612111 | R22: =MAX(R11:R16) -> 20.03512 | S22: =MAX(S11:S16) -> 14.568548
B23: Low | O23: =MIN(O11:O16) -> 0.33 | P23: =MIN(P11:P16) -> 0.48125714 | Q23: =MIN(Q11:Q16) -> 0.33688 | R23: =MIN(R11:R16) -> 5.3863561 | S23: =MIN(S11:S16) -> 3.458547
B25: Implied Valuation (C$)
B26: Mean | O26: =O20*$K$18/$J$18 -> 57.321276 | P26: =(P20*$H$18-($G$18-$F$18))/$J$18 -> 48.109364 | Q26: =(Q20*$I$18-($G$18-$F$18))/$J$18 -> 32.546222 | R26: N/A | S26: =(S20*$M$18-($G$18-$F$18))/$J$18 -> 43.016885
B27: Median | O27: =O21*$K$18/$J$18 -> 59.844854 | P27: =(P21*$H$18-($G$18-$F$18))/$J$18 -> 50.50882 | Q27: =(Q21*$I$18-($G$18-$F$18))/$J$18 -> 38.222004 | R27: N/A | S27: =(S21*$M$18-($G$18-$F$18))/$J$18 -> 28.008387
B28: High | O28: =O22*$K$18/$J$18 -> 80.754502 | P28: =(P22*$H$18-($G$18-$F$18))/$J$18 -> 75.308441 | Q28: =(Q22*$I$18-($G$18-$F$18))/$J$18 -> 43.633484 | R28: N/A | S28: =(S22*$M$18-($G$18-$F$18))/$J$18 -> 83.00251
B29: Low | O29: =O23*$K$18/$J$18 -> 23.793737 | P29: =(P23*$H$18-($G$18-$F$18))/$J$18 -> 18.510832 | Q29: =(Q23*$I$18-($G$18-$F$18))/$J$18 -> 15.783179 | R29: N/A | S29: =(S23*$M$18-($G$18-$F$18))/$J$18 -> 19.996987
A31: * | B31: Implied Upside
B32: Mean | O32: =O26/$C$6-1 -> 0.32995383 | P32: =P26/$C$6-1 -> 0.11622137 | Q32: =Q26/$C$6-1 -> -0.24487074 | R32: N/A | S32: =S26/$C$6-1 -> -0.0019330586
B33: Median | O33: =O27/$C$6-1 -> 0.38850525 | P33: =P27/$C$6-1 -> 0.17189294 | Q33: =Q27/$C$6-1 -> -0.11318269 | R33: N/A | S33: =S27/$C$6-1 -> -0.35015646
B34: High | O34: =O28/$C$6-1 -> 0.87364564 | P34: =P28/$C$6-1 -> 0.74728752 | Q34: =Q28/$C$6-1 -> 0.012373114 | R34: N/A | S34: =S28/$C$6-1 -> 0.92580336
B35: Low | O35: =O29/$C$6-1 -> -0.44794369 | P35: =P29/$C$6-1 -> -0.57051634 | Q35: =Q29/$C$6-1 -> -0.63380265 | R35: N/A | S35: =S29/$C$6-1 -> -0.53603494
B37: ¹ The peer set was selected to reflect a balanced mix of development-stage peers and high-grade single-asset producers, providing both a current trading benchmark and a forward-looking re-rating reference as Skeena transitions to production.
G41: Link for debt breakdown
G42: https://www.torys.com/work/2024/06/75631740-9d8c-4327-adea-365cb4b93607

Sheet PTA
B2: PRECEDENT TRANSACTIONS ANALYSIS
B4: DATA FRESHNESS
B5: Precedents Last Updated | D5: 46088 | E5: ← Update this date when refreshing comps
B6: Current Share Price | D6: ='NAV Model'!C8*'NAV Model'!$C$24 -> 43.1002
B8: Description | I8: Valuation
B9: Target Company | C9: Acquirer | D9: Transaction Date | E9: Domicile | F9: Share Price (LC) | G9: Market Cap ($mm LC) | H9: EV ($mm LC) | I9: Premium to Last Close (%) | J9: P/NAV
B10: Gold Road Resources | C10: Gold Fields Limited | D10: Sep-26-25 | E10: Australia | F10: 5.58 | G10: 7525 | H10: 6852.6 | I10: 0.14 | J10: 1.1
B11: Osisko Mining | C11: Gold Fields Limited | D11: 45590 | E11: Canada | F11: 6.73 | G11: 7687.9 | H11: 7649.2 | I11: 0.55 | J11: 0.96
B12: De Grey Mining | C12: Northern Star Resources | D12: 45782 | E12: Australia | F12: 8.48 | G12: 6421.5 | H12: 5662.8 | I12: 0.41 | J12: 1.1
B13: Pretium Resources | C13: Newcrest Mining | D13: 44629 | E13: Australia | F13: 1.615 | G13: 2391.4 | H13: 2566 | I13: 0.24 | J13: 1.5
B15: Skeena Resources | E15: Canada | F15: =Comps!E18 -> 43.1002 | G15: =Comps!F18 -> 5228.0543 | H15: =Comps!G18 -> 5181.5543 | I15: N/A | J15: =G15/('Cover Page'!G12*'NAV Model'!$C$24) -> 0.59776511
B16: Junior Gold
B17: Mean | I17: =AVERAGE(I10:I13) -> 0.335 | J17: =AVERAGE(J10:J13) -> 1.165
B18: Median | I18: =MEDIAN(I10:I13) -> 0.325 | J18: =MEDIAN(J10:J13) -> 1.1
B19: High | I19: =MAX(I10:I13) -> 0.55 | J19: =MAX(J10:J13) -> 1.5
B20: Low | I20: =MIN(I10:I13) -> 0.14 | J20: =MIN(J10:J13) -> 0.96
B22: Implied Valuation (C$)
B23: Mean | I23: =(I17+1)*$F$15 -> 57.538767 | J23: =J17*'Cover Page'!G13 -> 83.999102
B24: Median | I24: =(I18+1)*$F$15 -> 57.107765 | J24: =J18*'Cover Page'!G13 -> 79.312457
B25: High | I25: =(I19+1)*$F$15 -> 66.80531 | J25: =J19*'Cover Page'!G13 -> 108.15335
B26: Low | I26: =(I20+1)*$F$15 -> 49.134228 | J26: =J20*'Cover Page'!G13 -> 69.218145
A28: * | B28: Implied Upside
B29: Mean | I29: =I23/$D$6-1 -> 0.335 | J29: =J23/$D$6-1 -> 0.94892605
B30: Median | I30: =I24/$D$6-1 -> 0.325 | J30: =J24/$D$6-1 -> 0.84018768
B31: High | I31: =I25/$D$6-1 -> 0.55 | J31: =J25/$D$6-1 -> 1.5093468
B32: Low | I32: =I26/$D$6-1 -> 0.14 | J32: =J26/$D$6-1 -> 0.60598198

Sheet Broker Summary
B2: Broker Summary
C4: Bank | D4: Price Target (C$)
C5: UBS | D5: 60
C6: CIBC | D6: 58
C7: Our Target | D7: ='Cover Page'!G28 -> 56.233152
C8: Raymond James | D8: 50
C9: TD | D9: 49
C10: Scotiabank | D10: 44
C12: Analyst Target | D12: =AVERAGE(D8:D10,D5:D6) -> 52.2

Sheet Thesis Support ->

Sheet Thesis 2
B1: EXPANSION THESIS — PRODUCTION UPLIFT
B2: Incremental Gold & Silver Production from M&I Resource Expansion
B3: Compares base NAV Model production to expanded scenario across LOM
B5: GOLD PRODUCTION (oz)
B6: Scenario | C6: Units | D6: ='NAV Model'!F56 -> 2027 | E6: ='NAV Model'!G56 -> 2028 | F6: ='NAV Model'!H56 -> 2029 | G6: ='NAV Model'!I56 -> 2030 | H6: ='NAV Model'!J56 -> 2031 | I6: ='NAV Model'!K56 -> 2032 | J6: ='NAV Model'!L56 -> 2033 | K6: ='NAV Model'!M56 -> 2034 | ... O6: ='NAV Model'!Q56 -> 2038 | P6: LOM Total | Q6: LOM Avg
B7: Base Model | C7: oz | D7: 394939.48 | E7: 273095.31 | F7: 312215.67 | G7: 288199.08 | H7: 312215.67 | I7: 309093.51 | J7: 177455.91 | K7: 242834.41 | L7: 158776.34 | M7: 112397.64 | N7: 74718.279 | O7: 67673.413 | P7: =SUM(D7:O7) -> 2723614.7 | Q7: =AVERAGE(D7:O7) -> 226967.89
B8: Expansion | C8: oz | D8: 447311.54 | E8: 308708.32 | F8: 353065.88 | G8: 325906.97 | H8: 353065.88 | I8: 343659.08 | J8: 197357.3 | K8: 270067.88 | L8: 176582.85 | M8: 124966.94 | N8: 83097.81 | O8: 76052.944 | P8: =SUM(D8:O8) -> 3059843.4 | Q8: =AVERAGE(D8:O8) -> 254986.95
B9: Incremental Uplift | C9: oz | D9: =D8-D7 -> 52372.068 | E9: =E8-E7 -> 35613.006 | F9: =F8-F7 -> 40850.213 | G9: =G8-G7 -> 37707.889 | H9: =H8-H7 -> 40850.213 | I9: =I8-I7 -> 34565.565 | J9: =J8-J7 -> 19901.386 | K9: =K8-K7 -> 27233.475 | ... O9: =O8-O7 -> 8379.5308 | P9: =SUM(D9:O9) -> 336228.67 | Q9: =AVERAGE(D9:O9) -> 28019.056 | R9: =Q9/Q7 -> 0.12344943
B11: SILVER PRODUCTION (oz)
B12: Scenario | C12: Units | D12: =D6 -> 2027 | E12: =E6 -> 2028 | F12: =F6 -> 2029 | G12: =G6 -> 2030 | H12: =H6 -> 2031 | I12: =I6 -> 2032 | J12: =J6 -> 2033 | K12: =K6 -> 2034 | ... O12: =O6 -> 2038 | P12: LOM Total | Q12: LOM Avg
B13: Base Model | C13: oz | D13: 7915348.4 | E13: 7573507.8 | F13: 10111274 | G13: 8891250.2 | H13: 12955069 | I13: 6469635.3 | J13: 4188162.1 | K13: 9789444.9 | L13: 6215683.1 | M13: 2423545.9 | N13: 1402880.7 | O13: 1057295.2 | P13: =SUM(D13:O13) -> 78993097 | Q13: =AVERAGE(D13:O13) -> 6582758
B14: Expansion | C14: oz | D14: 8964985.6 | E14: 8561131.4 | F14: 11434230 | G14: 10054579 | H14: 14650107 | I14: 7193127 | J14: 4657857.5 | K14: 10887315 | L14: 6912761.7 | M14: 2694568.2 | N14: 1560211.4 | O14: 1188212.7 | P14: =SUM(D14:O14) -> 88759086 | Q14: =AVERAGE(D14:O14) -> 7396590.5
B15: Incremental Uplift | C15: oz | D15: =D14-D13 -> 1049637.2 | E15: =E14-E13 -> 987623.62 | F15: =F14-F13 -> 1322956.3 | G15: =G14-G13 -> 1163328.8 | H15: =H14-H13 -> 1695037.7 | I15: =I14-I13 -> 723491.72 | J15: =J14-J13 -> 469695.42 | K15: =K14-K13 -> 1097870 | ... O15: =O14-O13 -> 130917.55 | P15: =SUM(D15:O15) -> 9765989.8 | Q15: =AVERAGE(D15:O15) -> 813832.49 | R15: =Q15/Q13 -> 0.12363093
B17: Discounted FCF (US$ mm)
B18: Scenario | C18: Units | D18: =D12 -> 2027 | E18: =E12 -> 2028 | F18: =F12 -> 2029 | G18: =G12 -> 2030 | H18: =H12 -> 2031 | I18: =I12 -> 2032 | J18: =J12 -> 2033 | K18: =K12 -> 2034 | ... O18: =O12 -> 2038 | P18: LOM Total | Q18: LOM Avg
B19: Discounted FCF - Base | C19: US$ mm | D19: 1437.0418 | E19: 848.25439 | F19: 853.92355 | G19: 489.89565 | H19: 557.85819 | I19: 426.37281 | J19: 211.90273 | K19: 344.78036 | L19: 189.55061 | M19: 87.248808 | N19: 37.504676 | O19: -21.380932 | P19: =SUM(D19:O19) -> 5462.9526
B20: Discounted FCF - Expansion | C20: US$ mm | D20: 1640.9173 | E20: 972.02203 | F20: 977.57603 | G20: 565.18453 | H20: 641.07228 | I20: 479.71274 | J20: 241.14705 | K20: 388.22742 | L20: 215.58404 | M20: 101.60124 | N20: 46.104519 | O20: -13.669923 | P20: =SUM(D20:O20) -> 6255.4793 | Q20: =P20/P19-1 -> 0.14507295
B21: Incremental Uplift | C21: US$ mm | D21: =D20-D19 -> 203.87554 | E21: =E20-E19 -> 123.76763 | F21: =F20-F19 -> 123.65248 | G21: =G20-G19 -> 75.288888 | H21: =H20-H19 -> 83.214086 | I21: =I20-I19 -> 53.33993 | J21: =J20-J19 -> 29.244323 | K21: =K20-K19 -> 43.44706 | ... O21: =O20-O19 -> 7.7110089 | P21: =SUM(D21:O21) -> 792.52666 | Q21: =P21/P19 -> 0.14507295
B22: % Change | D22: =D21/D19 -> 0.14187169 | E22: =E21/E19 -> 0.14590863 | F22: =F21/F19 -> 0.1448051 | G22: =G21/G19 -> 0.15368352 | H22: =H21/H19 -> 0.1491671 | I22: =I21/I19 -> 0.12510162 | J22: =J21/J19 -> 0.13800824 | K22: =K21/K19 -> 0.12601373 | ... O22: =O21/O19 -> -0.36064887
B27: SUPPORTING GRAPHS
B28: Base Model | D28: =D7 -> 394939.48 | E28: =E7 -> 273095.31 | F28: =F7 -> 312215.67 | G28: =G7 -> 288199.08 | H28: =H7 -> 312215.67 | I28: =I7 -> 309093.51 | J28: =J7 -> 177455.91 | K28: =K7 -> 242834.41 | ... O28: =O7 -> 67673.413
B29: Incremental Uplift | D29: =D9 -> 52372.068 | E29: =E9 -> 35613.006 | F29: =F9 -> 40850.213 | G29: =G9 -> 37707.889 | H29: =H9 -> 40850.213 | I29: =I9 -> 34565.565 | J29: =J9 -> 19901.386 | K29: =K9 -> 27233.475 | ... O29: =O9 -> 8379.5308
B42: EXPANSION THESIS — TECHNICAL JUSTIFICATION
B43: Cutoff Grade Re-Rating & M&I Conversion Analysis at Spot Commodity Prices
B44: Source: Eskay Creek NI 43-101 Updated Feasibility Study, December 22, 2023
B46: CUTOFF GRADE RE-RATING ANALYSIS
B47: Parameter | C47: Units | D47: DFS Assumptions | E47: Model Base Case | F47: Δ Change
B48: Gold Price | C48: US$/oz | D48: 1700 | E48: ='Economic Assumptions'!I10 -> 3150 | F48: =(E48-D48)/D48 -> 0.85294118
B49: Silver Price | C49: US$/oz | D49: 23 | E49: ='Economic Assumptions'!I17 -> 42 | F49: =(E49-D49)/D49 -> 0.82608696
B50: Gold Recovery | C50: % | D50: 0.84 | E50: 0.84 | F50: —
B51: Silver Recovery | C51: % | D51: 0.88 | E51: 0.88 | F51: —
B52: Resource Cutoff Grade | C52: g/t AuEq | D52: 0.7 | E52: =D52*(D48/E48) -> 0.37777778 | F52: =(E52-D52)/D52 -> -0.46031746
B53: Reserve NSR Cutoff | C53: C$/t | D53: 24.45 | E53: =D53*((D48*D50)+(D49*D51))/((E48*E50)+(E49*E51)) -> 13.197911 | F53: =(E53-D53)/D53 -> -0.46020813
B55: ="AuEq Formula: AuEq = ((Au × $"&TEXT(D48,"#,##0")&" × "&TEXT(D50,"0.00")&") + (Ag × $"&TEXT(D49,"#,##0")&" × "&TEXT(D51,"0.00")&")) / ($"&TEXT(D48,"#,##0")&" × "&TEXT(D50,"0.00")&")" -> AuEq Formula: AuEq = ((Au × $1,700 × 0.84) + (Ag × $23 × 0.88)) / ($1,700 × 0.84)
B56: ="NSR Cut-off: C$"&TEXT(D53,"#,##0.00")&"/t based on processing costs of C$18.22/t + G&A of C$6.23/t" -> NSR Cut-off: C$24.45/t based on processing costs of C$18.22/t + G&A of C$6.23/t
B58: MINERAL RESOURCES & RESERVES — DFS TABLES (NI 43-101)
B60: Table 1-1: Mineral Resources — Open Pit (cutoff: 0.7 g/t AuEq)
B61: Category | C61: Tonnes (000) | D61: AuEq (g/t) | E61: Au (g/t) | F61: Ag (g/t) | G61: AuEq koz | H61: Au koz | I61: Ag koz
B62: Measured | C62: 27814 | D62: 4.6 | E62: 3.3 | F62: 87.9 | G62: 4077 | H62: 2964 | I62: 78560
B63: Indicated | C63: 22264 | D63: 2.1 | E63: 1.6 | F63: 32 | G63: 1468 | H63: 1144 | I63: 22876
B64: Total M&I | C64: 50078 | D64: 3.4 | E64: 2.6 | F64: 63 | G64: 5545 | H64: 4107 | I64: 101436
B65: Inferred | C65: 652 | D65: 1.9 | E65: 1.5 | F65: 32.4 | G65: 40 | H65: 30 | I65: 680
B67: Table 1-2: Mineral Resources — Underground (cutoff: 3.2 g/t AuEq)
B68: Category | C68: Tonnes (000) | D68: AuEq (g/t) | E68: Au (g/t) | F68: Ag (g/t) | G68: AuEq koz | H68: Au koz | I68: Ag koz
B69: Measured | C69: 834 | D69: 7.3 | E69: 5.3 | F69: 142.9 | G69: 196 | H69: 142 | I69: 3831
B70: Indicated | C70: 988 | D70: 4.9 | E70: 4.1 | F70: 55.7 | G70: 156 | H70: 131 | I70: 1768
B71: Total M&I | C71: 1821 | D71: 6 | E71: 4.7 | F71: 95.6 | G71: 352 | H71: 273 | I71: 5599
B72: Inferred | C72: 272 | D72: 4.6 | E72: 4.2 | F72: 25.4 | G72: 40 | H72: 37 | I72: 222
B74: Table 1-3: Mineral Reserves (NSR cutoff: C$24.45/t)
B75: Category | C75: Tonnes (000) | D75: AuEq (g/t) | E75: Au (g/t) | F75: Ag (g/t) | G75: AuEq koz | H75: Au koz | I75: Ag koz
B76: Proven | C76: 27954 | D76: 4.1 | E76: 3 | F76: 80.9 | G76: 3675 | H76: 2657 | I76: 72661
B77: Probable | C77: 11889 | D77: 2.3 | E77: 1.8 | F77: 40.1 | G77: 894 | H77: 680 | I77: 15308
B78: Total P&P | C78: 39843 | D78: 3.6 | E78: 2.6 | F78: 68.7 | G78: 4569 | H78: 3336 | I78: 87969
B79: Reserve pricing: US$1,800/oz Au, US$23/oz Ag; recoveries: 83% Au, 91% Ag
B82: M&I TO P&P CONVERSION GAP ANALYSIS
B83: Metric | D83: Tonnes (000) | E83: AuEq (g/t) | F83: AuEq koz | G83: % of M&I
B84: Total M&I Resources (Open Pit) | D84: =C64 -> 50078 | E84: =D64 -> 3.4 | F84: =G64 -> 5545 | G84: 1
B85: Total P&P Reserves | D85: =C78 -> 39843 | E85: =D78 -> 3.6 | F85: =G78 -> 4569 | G85: =D85/D84 -> 0.79561883
B86: Unconverted M&I Gap | D86: =D84-D85 -> 10235 | F86: =F84-F85 -> 976 | G86: =D86/D84 -> 0.20438117
B87: Converted Tonnes (Cutoff Δ × Gap) | D87: =ABS(D88)*D86 -> 4710.2302
B88: NSR Cutoff Reduction at Model Prices | D88: =F53 -> -0.46020813
B89: Implied M&I Conversion % | D89: =D87/D84 -> 0.094057874 | E89: ="("&TEXT(D87,"#,##0")&"kt of "&TEXT(D86,"#,##0")&"kt unconverted gap)" -> (4,710kt of 10,235kt unconverted gap)
B91: THESIS DEFENSIBILITY STATEMENT
B93: ="At model prices ("&TEXT(E48,"$#,##0")&" Au, "&TEXT(E49,"$#,##0")&" Ag), the NSR cutoff drops "&TEXT(ABS(F53),"0%")&" vs. DFS assumptions — from" -> At model prices ($3,150 Au, $42 Ag), the NSR cutoff drops 46% vs. DFS assumptions — from
B94: =TEXT(D53,"$#,##0.00")&"/t to "&TEXT(E53,"$#,##0.00")&"/t. Assuming a linear grade-tonnage distribution, "&TEXT(ABS(F53),"0%")&" of the "&TEXT(D86,"#,##0")&"kt unconverted M&I gap clears the new threshold ("&TEXT(D87,"#,##0")&"kt, or "&TEXT(D89,"0.0%")&" of total M&I)." -> $24.45/t to $13.20/t. Assuming a linear grade-tonnage distribution, 46% of the 10,235kt unconverted M&I gap clears the new threshold (4,710kt, or 9.4% of total M&I).
B96: Key Assumption — Linear Grade-Tonnage:
B97: Assumes uniform tonnage across grade bins. In practice, deposits are log-normal (concave) — a cutoff reduction typically captures more
B98: tonnage than the linear case but at lower average grade. These biases offset; linear is a reasonable middle ground without block model data.
B100: Supporting Arguments:
B101: ="1. AuEq cutoff falls "&TEXT(ABS(F52),"0%")&" from "&TEXT(D52,"0.00")&" to "&TEXT(E52,"0.00")&" g/t — substantial expansion of economic envelope" -> 1. AuEq cutoff falls 46% from 0.70 to 0.38 g/t — substantial expansion of economic envelope
B102: ="2. Conversion is "&TEXT(D89,"0.0%")&" of total M&I ("&TEXT(D87,"#,##0")&"kt of "&TEXT(D84,"#,##0")&"kt) — conservative vs. the "&TEXT(G86,"0%")&" unconverted gap" -> 2. Conversion is 9.4% of total M&I (4,710kt of 50,078kt) — conservative vs. the 20% unconverted gap
B103: ="3. Underground M&I ("&TEXT(C71,"#,##0")&"kt at "&TEXT(D71,"0.0")&" g/t AuEq) provides additional upside not included in conversion" -> 3. Underground M&I (1,821kt at 6.0 g/t AuEq) provides additional upside not included in conversion

Sheet Mine Overview
A4: Gold:Silver price ratio | B4: ='Economic Assumptions'!C7/'Economic Assumptions'!C8 -> 75
B6: Units | C6: ='NAV Model'!F56 -> 2027 | D6: ='NAV Model'!G56 -> 2028 | E6: ='NAV Model'!H56 -> 2029 | F6: ='NAV Model'!I56 -> 2030 | G6: ='NAV Model'!J56 -> 2031 | H6: ='NAV Model'!K56 -> 2032 | I6: ='NAV Model'!L56 -> 2033 | J6: ='NAV Model'!M56 -> 2034 | ... N6: ='NAV Model'!Q56 -> 2038
A8: AISC (US$/oz AuEq) | B8: US$/oz | C8: ='NAV Model'!F90 -> 602.60928 | D8: ='NAV Model'!G90 -> 825.31359 | E8: ='NAV Model'!H90 -> 724.7713 | F8: ='NAV Model'!I90 -> 751.48141 | G8: ='NAV Model'!J90 -> 698.5213 | H8: ='NAV Model'!K90 -> 506.83894 | I8: ='NAV Model'!L90 -> 834.42631 | J8: ='NAV Model'!M90 -> 626.73461 | ... N8: ='NAV Model'!Q90 -> 1942.7062
A10: Au Produced | B10: oz | C10: ='NAV Model'!F62 -> 394939.48 | D10: ='NAV Model'!G62 -> 273095.31 | E10: ='NAV Model'!H62 -> 312215.67 | F10: ='NAV Model'!I62 -> 288199.08 | G10: ='NAV Model'!J62 -> 312215.67 | H10: ='NAV Model'!K62 -> 309093.51 | I10: ='NAV Model'!L62 -> 177455.91 | J10: ='NAV Model'!M62 -> 242834.41 | ... N10: ='NAV Model'!Q62 -> 67673.413
A11: Ag Produced | B11: oz | C11: ='NAV Model'!F65 -> 7915348.4 | D11: ='NAV Model'!G65 -> 7573507.8 | E11: ='NAV Model'!H65 -> 10111274 | F11: ='NAV Model'!I65 -> 8891250.2 | G11: ='NAV Model'!J65 -> 12955069 | H11: ='NAV Model'!K65 -> 6469635.3 | I11: ='NAV Model'!L65 -> 4188162.1 | J11: ='NAV Model'!M65 -> 9789444.9 | ... N11: ='NAV Model'!Q65 -> 1057295.2
A12: AuEq Ag Produced | B12: oz | C12: =C11/$B$4 -> 105537.98 | D12: =D11/$B$4 -> 100980.1 | E12: =E11/$B$4 -> 134816.98 | F12: =F11/$B$4 -> 118550 | G12: =G11/$B$4 -> 172734.26 | H12: =H11/$B$4 -> 86261.803 | I12: =I11/$B$4 -> 55842.161 | J12: =J11/$B$4 -> 130525.93 | ... N12: =N11/$B$4 -> 14097.269
A13: Annual Production (koz AuEq) | B13: koz | C13: =SUM(C12,C10)/1000 -> 500.47746 | D13: =SUM(D12,D10)/1000 -> 374.07541 | E13: =SUM(E12,E10)/1000 -> 447.03265 | F13: =SUM(F12,F10)/1000 -> 406.74908 | G13: =SUM(G12,G10)/1000 -> 484.94993 | H13: =SUM(H12,H10)/1000 -> 395.35531 | I13: =SUM(I12,I10)/1000 -> 233.29807 | J13: =SUM(J12,J10)/1000 -> 373.36034 | ... N13: =SUM(N12,N10)/1000 -> 81.770682
A15: Total Opex (US$ mm) | C15: =C6 -> 2027 | D15: =D6 -> 2028 | E15: =E6 -> 2029 | F15: =F6 -> 2030 | G15: =G6 -> 2031 | H15: =H6 -> 2032 | I15: =I6 -> 2033 | J15: =J6 -> 2034 | ... N15: =N6 -> 2038
A16: Total Opex (US$ mm) | B16: ='NAV Model'!C81 -> US$ mm | C16: ='NAV Model'!F81-'NAV Model'!F79 -> 1132.2133 | D16: ='NAV Model'!G81-'NAV Model'!G79 -> 1475.1338 | E16: ='NAV Model'!H81-'NAV Model'!H79 -> 1389.3621 | F16: ='NAV Model'!I81-'NAV Model'!I79 -> 1086.5898 | G16: ='NAV Model'!J81-'NAV Model'!J79 -> 1362.9114 | H16: ='NAV Model'!K81-'NAV Model'!K79 -> 710.42258 | I16: ='NAV Model'!L81-'NAV Model'!L79 -> 918.09696 | J16: ='NAV Model'!M81-'NAV Model'!M79 -> 1384.7518 | ... N16: ='NAV Model'!Q81-'NAV Model'!Q79 -> 704.84415
A17: Total Capex (US$mm) | B17: ='NAV Model'!C88 -> US$ mm | C17: ='NAV Model'!F88 -> 34.142336 | D17: ='NAV Model'!G88 -> 34.142336 | E17: ='NAV Model'!H88 -> 34.142336 | F17: ='NAV Model'!I88 -> 34.142336 | G17: ='NAV Model'!J88 -> 34.142336 | H17: ='NAV Model'!K88 -> 40.492701 | I17: ='NAV Model'!L88 -> 34.142336 | J17: ='NAV Model'!M88 -> 34.142336 | ... N17: ='NAV Model'!Q88 -> 161.73358

Sheet Data Inputs ->

Sheet Reserve & Resource
A1: MINERAL RESERVE & RESOURCE STATEMENT
A2: Source: Technical Report, Section 14-15
A4: Category | B4: Tonnes (000) | C4: AuEq (g/t) | D4: Au (g/t) | E4: Ag (g/t) | F4: AuEq Oz (000) | G4: Au Oz (000) | H4: Ag Oz (000)
A5: Measured | B5: 27814 | C5: 4.6 | D5: 3.3 | E5: 87.9 | F5: 4077 | G5: 2964 | H5: 78560
A6: Indicated | B6: 22264 | C6: 2.1 | D6: 1.6 | E6: 32 | F6: 1468 | G6: 1144 | H6: 22876
A7: Total Measured + Indicated | B7: 50078 | C7: 3.4 | D7: 2.6 | E7: 63 | F7: 5545 | G7: 4107 | H7: 101436
A8: Inferred | B8: 652 | C8: 1.9 | D8: 1.5 | E8: 32.4 | F8: 40 | G8: 30 | H8: 680
A11: MINERAL RESERVE STATEMENT
A13: Category | B13: Tonnes (000) | C13: AuEq (g/t) | D13: Au (g/t) | E13: Ag (g/t) | F13: AuEq Oz (000) | G13: Au Oz (000) | H13: Ag Oz (000)
A14: Proven | B14: 27954 | C14: 4.1 | D14: 3 | E14: 80.9 | F14: 3675 | G14: 2657 | H14: 72661
A15: Probable | B15: 11889 | C15: 2.3 | D15: 1.8 | E15: 40.1 | F15: 894 | G15: 680 | H15: 15308
A16: Total Proven + Probable | B16: 39843 | C16: 3.6 | D16: 2.6 | E16: 68.7 | F16: 4569 | G16: 3336 | H16: 87969
A18: EXPANSION SCENARIO — M&I CONVERSION
E19: Conversion % | F19: ='Thesis 2'!D89 -> 0.094057874
A20: Category | B20: Tonnes (000) | C20: AuEq (g/t) | D20: AuEq Oz (000)
A21: Total M&I Resources (OP) | B21: =B7 -> 50078 | C21: =C7 -> 3.4 | D21: =F7 -> 5545
A22: ="Cutoff-Implied Conversion ("&TEXT(F19,"0.0%")&")" -> Cutoff-Implied Conversion (9.4%) | B22: =B21*F19 -> 4710.2302 | C22: =C21 -> 3.4 | D22: =D21*F19 -> 521.55091
A24: Existing P&P Reserves | B24: =B16 -> 39843 | C24: =C16 -> 3.6 | D24: =F16 -> 4569
A25: (+) Converted M&I | B25: =B22 -> 4710.2302 | C25: =C22 -> 3.4 | D25: =D22 -> 521.55091
A27: New P&P Total | B27: =B24+B25 -> 44553.23 | D27: =D24+D25 -> 5090.5509

Sheet Production Schedule
A1: LIFE OF MINE PRODUCTION SCHEDULE
A2: Source: Eskay Creek NI 43-101 Updated Feasibility Study, Table 16-3, December 22, 2023
A4: MINING SUMMARY
A5: Description | B5: Units | C5: Y-3 | D5: Y-2 | E5: Y-1 | F5: Y1 | G5: Y2 | H5: Y3 | I5: Y4 | J5: Y5 | K5: Y6 | L5: Y7 | M5: Y8 | N5: Y9 | O5: Y10 | P5: Y11 | Q5: Y12 | R5: Total
A6: NAG Waste | B6: Mt | C6: 1.62 | D6: 6.29 | E6: 9.26 | F6: 24.97 | G6: 21.31 | H6: 26.01 | I6: 21.29 | J6: 20.36 | K6: 10.03 | L6: 11.9 | M6: 11.48 | N6: 1.99 | O6: 0 | P6: 0 | Q6: 0 | R6: 166.5
A7: PAG Waste | B7: Mt | C7: 0.33 | D7: 2.27 | E7: 8.01 | F7: 15.26 | G7: 18.07 | H7: 20.01 | I7: 18.81 | J7: 17.93 | K7: 22.29 | L7: 8.84 | M7: 9.7 | N7: 9.85 | O7: 0 | P7: 0 | Q7: 0 | R7: 151.39
A8: Mined Waste | B8: Mt | C8: 1.95 | D8: 8.57 | E8: 17.27 | F8: 40.23 | G8: 39.38 | H8: 46.03 | I8: 40.1 | J8: 38.29 | K8: 32.32 | L8: 20.74 | M8: 21.18 | N8: 11.85 | O8: 0 | P8: 0 | Q8: 0 | R8: 317.89
A9: Mined Ore | B9: Mt | C9: 0 | D9: 0.06 | E9: 1.49 | F9: 5.69 | G9: 4.74 | H9: 3.93 | I9: 4.79 | J9: 5.21 | K9: 5.02 | L9: 1.38 | M9: 3.47 | N9: 4.06 | O9: 0 | P9: 0 | Q9: 0 | R9: 39.84
A10: Au Grade | B10: g/t | C10: 0 | D10: 4.2 | E10: 1.7 | F10: 3 | G10: 2.5 | H10: 3.3 | I10: 2.7 | J10: 2.7 | K10: 2.6 | L10: 2.8 | M10: 2.6 | N10: 1.5 | O10: 0 | P10: 0 | Q10: 0 | R10: 2.6
A11: Ag Grade | B11: g/t | C11: 0 | D11: 28.5 | E11: 48.6 | F11: 57.5 | G11: 58.6 | H11: 93.9 | I11: 71.4 | J11: 92.2 | K11: 46 | L11: 66.3 | M11: 93.6 | N11: 53.9 | O11: 0 | P11: 0 | Q11: 0 | R11: 68.7
A12: Total Mined | B12: Mt | C12: 1.95 | D12: 8.63 | E12: 18.77 | F12: 45.92 | G12: 44.12 | H12: 49.96 | I12: 44.89 | J12: 43.5 | K12: 37.34 | L12: 22.12 | M12: 24.65 | N12: 15.9 | O12: 0 | P12: 0 | Q12: 0 | R12: 357.73
A14: PROCESSED MATERIAL (MILL FEED)
A15: Mill Feed | B15: Mt | C15: 0 | D15: 0 | E15: 0.68 | F15: 2.96 | G15: 3.01 | H15: 3 | I15: 3 | J15: 3 | K15: 3.51 | L15: 3.5 | M15: 3.5 | N15: 3.5 | O15: 3.51 | P15: 3.5 | Q15: 3.17 | R15: 39.84
A16: Au Grade | B16: g/t | C16: 0 | D16: 0 | E16: 2 | F16: 5 | G16: 3.4 | H16: 3.9 | I16: 3.6 | J16: 3.9 | K16: 3.3 | L16: 1.9 | M16: 2.6 | N16: 1.7 | O16: 1.2 | P16: 0.8 | Q16: 0.8 | R16: 2.6
A17: Ag Grade | B17: g/t | C17: 0 | D17: 0 | E17: 53.4 | F17: 91.4 | G17: 86 | H17: 115.2 | I17: 101.3 | J17: 147.6 | K17: 63 | L17: 40.9 | M17: 95.6 | N17: 60.7 | O17: 23.6 | P17: 13.7 | Q17: 11.4 | R17: 68.7
A19: STOCKPILE & MATERIAL MOVEMENT
A20: Medium Grade | B20: Mt | C20: 0 | D20: 0.06 | E20: 1.25 | F20: 2.44 | G20: 1.34 | H20: 1.59 | I20: 1.62 | J20: 1.55 | K20: 0.81 | L20: 0.37 | M20: 0.35 | N20: 0.28 | O20: 0 | P20: 0 | Q20: 0
A21: Low Grade | B21: Mt | C21: 0 | D21: 0 | E21: 0.25 | F21: 0.98 | G21: 0.84 | H21: 0.51 | I21: 0.52 | J21: 0.67 | K21: 0.86 | L21: 0.16 | M21: 0.6 | N21: 0.65 | O21: 0 | P21: 0 | Q21: 0
A22: Total Stockpile Balance | B22: Mt | C22: 0 | D22: 0.06 | E22: 1.49 | F22: 3.41 | G22: 2.18 | H22: 2.1 | I22: 2.14 | J22: 2.21 | K22: 1.67 | L22: 0.53 | M22: 0.96 | N22: 0.93 | O22: 0 | P22: 0 | Q22: 0 | R22: 17.68
A23: Total Stockpile Reclaim | B23: Mt | C23: 0 | D23: 0 | E23: 0.68 | F23: 0.69 | G23: 0.45 | H23: 1.17 | I23: 0.35 | J23: 0 | K23: 0.16 | L23: 2.64 | M23: 0.98 | N23: 0.37 | O23: 3.51 | P23: 3.5 | Q23: 3.17 | R23: 17.68
A24: Total Material Movement | B24: Mt | C24: 1.95 | D24: 8.63 | E24: 19.45 | F24: 46.61 | G24: 44.56 | H24: 51.13 | I24: 45.24 | J24: 43.5 | K24: 37.5 | L24: 24.77 | M24: 25.63 | N24: 16.28 | O24: 3.51 | P24: 3.5 | Q24: 3.17 | R24: 375.41

Sheet Operating Costs
A1: OPERATING COST ESTIMATES
A2: Paste the LOM operating cost breakdown from the technical report below (Section 21)
B4: Initial (Years 1–5) | D4: Expansion (Year 6+) | F4: LOM Total
A5: Cost Category | B5: C$M | C5: C$/t milled | D5: C$M/a | E5: C$/t milled | F5: C$M | G5: C$/t milled
A6: Mining | B6: 710.5 | C6: 45.4 | D6: 347 | E6: 14.34 | F6: 1057.5 | G6: 26.54
A7: Processing | B7: 313.5 | C7: 20.03 | D7: 450 | E7: 18.6 | F7: 763.5 | G7: 19.16
A8: G&A | B8: 150.1 | C8: 9.59 | D8: 176.1 | E8: 7.28 | F8: 326.2 | G8: 8.19
A9: Total | B9: 1174.2 | C9: 75.03 | D9: 973.1 | E9: 40.22 | F9: 2147.3 | G9: 53.89
A11: Note: Costs are in C$/t milled from the technical report. Convert to USD/oz for the NAV model using the FX rate and production schedule.

Sheet Concentrate Overview
A1: CONCENTRATE GRADE SUMMARY
A2: Annual & Life-of-Mine Payable / Deleterious Element Grades
A4: Status | B4: Element | C4: Unit | D4: Minimum (Annual) | E4: Maximum (Annual) | F4: Average (LOM)
A5: Payable | B5: Au | C5: g/t | D5: 17 | E5: 94 | F5: 55
B6: Ag | C6: g/t | D6: 283 | E6: 2943 | F6: 1588
B7: Pb | C7: % | D7: 2.19 | E7: 13.93 | F7: 8.06
B8: Zn | C8: % | D8: 4.02 | E8: 21.03 | F8: 12.79
B9: Cu | C9: % | D9: 0.48 | E9: 2.05 | F9: 1.14
A10: Deleterious | B10: As | C10: % | D10: 0.69 | E10: 5.96 | F10: 1.5
B11: Hg | C11: % | D11: 0.03 | E11: 0.32 | F11: 0.08
A12: Payable / Deleterious | B12: Sb | C12: % | D12: 0.74 | E12: 5.72 | F12: 1.78

Sheet Capital Costs
A1: CAPITAL COST ESTIMATES
A2: Paste the capex schedule from the technical report below (Section 21)
A4: Description | B4: Initial (C$M) | C4: Sustaining (C$M) | D4: Expansion (C$M) | E4: Closure (C$M)
A5: Mining | B5: 113.7 | C5: 426 | D5: — | E5: —
A6: Ore Crushing and Reclaim | B6: 38 | C6: 3 | D6: — | E6: —
A7: Process Plant | B7: 171.8 | C7: 2 | D7: 8 | E7: —
A8: Tailings Reclaim and Water Treatment | B8: 21.7 | C8: 65.3 | D8: — | E8: —
A9: On-Site Infrastructure | B9: 98.6 | C9: 52 | D9: — | E9: —
A10: Off-Site Infrastructure | B10: 30.3 | C10: — | D10: — | E10: —
A11: Owner's Costs | B11: 92.6 | C11: — | D11: — | E11: —
A12: Indirect Costs | B12: 97.5 | C12: 13 | D12: 0.7 | E12: —
A13: Subtotal | B13: 664.2 | C13: 561.3 | D13: 8.7 | E13: —
A14: Contingency | B14: 48.7 | C14: — | D14: — | E14: —
A15: Closure | B15: — | C15: — | D15: — | E15: 174.8
A16: Total | B16: 712.9 | C16: 561.3 | D16: 8.7 | E16: 174.8

Sheet Financial Statements ->

Sheet Statement of Loss
A1: CONSOLIDATED STATEMENTS OF LOSS AND COMPREHENSIVE LOSS
A2: Source: Skeena Gold & Silver, Years ended December 31
A3: (expressed in thousands of Canadian dollars, except per share amounts)
B5: 2024 | C5: 2023
A6: Accretion | B6: 1013 | C6: 339
A7: Administrative compensation | B7: 5892 | C7: 6378
A8: Change in FV of convertible debenture | B8: 3153 | C8: 164
A9: Change in FV of derivative liability | B9: -7737 | C9: 0
A10: Communications | B10: 1579 | C10: 1316
A11: Consulting | B11: 4231 | C11: 1140
A12: Depreciation | B12: 859 | C12: 392
A13: Exploration and evaluation | B13: 146922 | C13: 91855
A14: Flow-through share premium recovery | B14: -17429 | C14: -5078
A15: Interest income | B15: -3694 | C15: -2040
A16: Share-based payments | B16: 8799 | C16: 8856
A17: Other expenses (net) | B17: 8351 | C17: 5302
... A23: Wtd avg shares outstanding | B23: 99128496 | C23: 84353282

Sheet Balance Sheet
A1: CONSOLIDATED STATEMENTS OF FINANCIAL POSITION
A2: Source: Skeena Gold & Silver
A3: (expressed in thousands of Canadian dollars)
B5: 45657 | C5: 45291
A6: ASSETS
A7: Cash and cash equivalents | B7: 96941 | C7: 91135
A8: Marketable securities | B8: 949 | C8: 1554
A9: Receivables | B9: 2351 | C9: 3225
A10: Other current assets | B10: 698 | C10: 1588
A11: Total current assets | B11: 100939 | C11: 97502
A12: Deposits | B12: 5083 | C12: 2102
A13: Exploration and evaluation interests | B13: 18662 | C13: 62414
A14: Mineral property, plant and equipment | B14: 144220 | C14: 32969
A15: Other non-current assets | B15: 5487 | C15: 0
A16: Total assets | B16: 274391 | C16: 194987
A18: LIABILITIES
A19: Accounts payable and accrued liabilities | B19: 57285 | C19: 20588
A20: Current portion of lease liabilities | B20: 6303 | C20: 1061
A21: Flow-through share premium liability | B21: 5708 | C21: 3137
A22: Other current liabilities | B22: 721 | C22: 449
A23: Total current liabilities | B23: 70017 | C23: 25235
A24: Lease liabilities (non-current) | B24: 7230 | C24: 8546
A25: Derivative liability (Gold Stream) | B25: 63886 | C25: 0
A26: Provision for closure and reclamation | B26: 38499 | C26: 13654
A27: Other non-current liabilities | B27: 4146 | C27: 242
A28: Total liabilities | B28: 183778 | C28: 70452
A30: SHAREHOLDERS' EQUITY
A31: Capital stock | B31: 670126 | C31: 552397
A32: Commitment to issue shares | B32: 250 | C32: 750
A33: Reserves | B33: 47346 | C33: 48299
A34: Deficit | B34: -627109 | C34: -476911
A35: Total shareholders' equity | B35: 90613 | C35: 124535
A36: Total liabilities and equity | B36: 274391 | C36: 194987

Sheet Cash Flow Statement
A1: CASH FLOW STATEMENT
A2: Source: Skeena Gold & Silver, Annual Financial Statements, Years ended December 31
A3: (expressed in thousands of Canadian dollars)
B5: 2024 | C5: 2023
A6: OPERATING ACTIVITIES
A7: Loss for the year | B7: -151939 | C7: -108980
A8: Accretion | B8: 1608 | C8: 546
A9: Change in FV of convertible debenture | B9: 3153 | C9: 164
A10: Change in FV of derivative liability | B10: -7737 | C10: 0
A11: Depreciation | B11: 8223 | C11: 2400
A12: E&E expenses capitalized | B12: -857 | C12: 0
A13: Flow-through share premium recovery | B13: -17429 | C13: -5078
A14: Share-based payments | B14: 13126 | C14: 11987
A15: Other non-cash items | B15: -2878 | C15: -22
A16: Changes in working capital | B16: 22846 | C16: 8351
A17: Net cash used in operating activities | B17: -127900 | C17: -90598
A19: INVESTING ACTIVITIES
A20: Proceeds from sale of marketable securities | B20: 38 | C20: 396
A21: Deposits paid | B21: -12469 | C21: -125
A22: Exploration and evaluation expenditures | B22: -8799 | C22: -14354
A23: Net proceeds from sale of NSR | B23: 0 | C23: 56000
A24: Additions to mineral property, PP&E | B24: -2213 | C24: -8749
A25: Other investing activities | B25: -387 | C25: -1900
A26: Net cash provided by (used in) investing | B26: -23830 | C26: 31268
A28: FINANCING ACTIVITIES
A29: Lease payments | B29: -8582 | C29: -991
A30: Repayment of convertible debenture | B30: -25928 | C30: 0
A31: Proceeds from Gold Stream | B31: 71623 | C31: 0
A32: Equity proceeds (placements, options, warrants) | B32: 125633 | C32: 89911
A33: Share issue costs & other | B33: -5975 | C33: -4057
A34: Net cash provided by financing | B34: 156771 | C34: 109863
A36: Effect of FX on cash | B36: 765 | C36: 0
A37: Change in cash during the year | B37: 5806 | C37: 50533
A39: Cash, beginning of year | B39: 91135 | C39: 40602
A40: Cash, end of year | B40: 96941 | C40: 91135
